Workbook
Name GST_Rate: 'S03-06 Done'!$G$1
Name Taxable: 'S03-06 Done'!$B$2:$B$7
Name North: 'S03-06 Done'!$F$4:$F$9
Name South: 'S03-06 Done'!$G$4:$G$9
Name East: 'S03-06 Done'!$H$4:$H$9
Name West: 'S03-06 Done'!$I$4:$I$9

Sheet Start here
A1: Excel Mastery for Mac | Section S03: Formula foundations
A2: Each lesson has a practice sheet (same name as the lesson id) and a finished copy ('Done' or 'Answers'). Yellow cells are the ones you fill in.
A4: Lesson | B4: Type | C4: Title | D4: Practice sheet | E4: Finished sheet
A5: S03-01 | B5: demo | C5: Your first formula: operators and order | D5: S03-01 | E5: S03-01 Done
A6: S03-02 | B6: demo | C6: Relative, absolute and mixed references | D6: S03-02 | E6: S03-02 Done
A7: S03-03 | B7: demo | C7: SUM, AVERAGE, MIN, MAX and the COUNT family | D7: S03-03 | E7: S03-03 Done
A8: S03-04 | B8: demo | C8: Rounding the right way | D8: S03-04 | E8: S03-04 Done
A9: S03-05 | B9: demo | C9: Formulas across sheets and files | D9: S03-05 | E9: S03-05 Done
A10: S03-06 | B10: demo | C10: Named ranges and the Name Manager | D10: S03-06 | E10: S03-06 Done
A11: S03-07 | B11: demo | C11: Every error value and how to fix it | D11: S03-07 | E11: S03-07 Done
A12: S03-08 | B12: demo | C12: Auditing formulas | D12: S03-08 | E12: S03-08 Done
A13: S03-09 | B13: demo | C13: Calculation settings and circular references | D13: S03-09 | E13: S03-09 Done
A14: S03-10 | B14: challenge | C14: Challenge 3: a sales commission sheet | D14: S03-10 | E14: S03-10 Answers
A16: Lesson S03-05 also uses the sheets Apr, May, Jun and Targets FY27.

Sheet S03-01
A1: Item | B1: Qty | C1: Rate (₹) | D1: Amount (₹) | F1: Client | G1: Mehta Interiors
A2: Ergonomic office chair | B2: 12 | C2: 8500 | F2: Quote title
A3: Workstation desk | B3: 6 | C3: 14200
A4: Steel filing cabinet | B4: 4 | C4: 11800 | F4: Chair rate in 3 years at 6% a year
A5: Visitor chair | B5: 10 | C5: 3600
A6: Whiteboard 6x4 ft | B6: 2 | C6: 5400 | F6: Challenge: chair rate incl. 18% GST
A8: Subtotal
A9: Discount 5%
A10: After discount
A11: GST 18%
A12: Grand total
A13: Grand total in one formula

Sheet S03-01 Done
A1: Item | B1: Qty | C1: Rate (₹) | D1: Amount (₹) | F1: Client | G1: Mehta Interiors
A2: Ergonomic office chair | B2: 12 | C2: 8500 | D2: =B2*C2 | F2: Quote title | G2: ="Quote for "&G1
A3: Workstation desk | B3: 6 | C3: 14200 | D3: =B3*C3
A4: Steel filing cabinet | B4: 4 | C4: 11800 | D4: =B4*C4 | F4: Chair rate in 3 years at 6% a year | G4: =C2*(1+6%)^3
A5: Visitor chair | B5: 10 | C5: 3600 | D5: =B5*C5
A6: Whiteboard 6x4 ft | B6: 2 | C6: 5400 | D6: =B6*C6 | F6: Challenge: chair rate incl. 18% GST | G6: =C2*(1+18%)
A8: Subtotal | D8: =D2+D3+D4+D5+D6
A9: Discount 5% | D9: =D8*5%
A10: After discount | D10: =D8-D9
A11: GST 18% | D11: =D10*18%
A12: Grand total | D12: =D10+D11
A13: Grand total in one formula | D13: =(D8-D9)*1.18

Sheet S03-02
A1: Invoice No | B1: Taxable Value (₹) | C1: GST (₹) | E1: GST rate | F1: 0.18
A2: SAF/26-27/0201 | B2: 125000
A3: SAF/26-27/0202 | B3: 84600
A4: SAF/26-27/0203 | B4: 236500
A5: SAF/26-27/0204 | B5: 47800
A6: SAF/26-27/0205 | B6: 158900
A7: SAF/26-27/0206 | B7: 92300
A10: Price list after discount
A11: Product | B11: List Price (₹) | C11: 0.05 | D11: 0.1 | E11: 0.15
A12: Ergonomic office chair | B12: 8500
A13: Executive desk | B13: 24600
A14: Steel filing cabinet | B14: 11800
A15: Bookshelf | B15: 7200
A16: Conference table | B16: 46500
A18: Challenge: add a 20% column in F11:F16

Sheet S03-02 Done
A1: Invoice No | B1: Taxable Value (₹) | C1: GST (₹) | E1: GST rate | F1: 0.18
A2: SAF/26-27/0201 | B2: 125000 | C2: =B2*$F$1
A3: SAF/26-27/0202 | B3: 84600 | C3: =B3*$F$1
A4: SAF/26-27/0203 | B4: 236500 | C4: =B4*$F$1
A5: SAF/26-27/0204 | B5: 47800 | C5: =B5*$F$1
A6: SAF/26-27/0205 | B6: 158900 | C6: =B6*$F$1
A7: SAF/26-27/0206 | B7: 92300 | C7: =B7*$F$1
A10: Price list after discount
A11: Product | B11: List Price (₹) | C11: 0.05 | D11: 0.1 | E11: 0.15 | F11: 0.2
A12: Ergonomic office chair | B12: 8500 | C12: =$B12*(1-C$11) | D12: =$B12*(1-D$11) | E12: =$B12*(1-E$11) | F12: =$B12*(1-F$11)
A13: Executive desk | B13: 24600 | C13: =$B13*(1-C$11) | D13: =$B13*(1-D$11) | E13: =$B13*(1-E$11) | F13: =$B13*(1-F$11)
A14: Steel filing cabinet | B14: 11800 | C14: =$B14*(1-C$11) | D14: =$B14*(1-D$11) | E14: =$B14*(1-E$11) | F14: =$B14*(1-F$11)
A15: Bookshelf | B15: 7200 | C15: =$B15*(1-C$11) | D15: =$B15*(1-D$11) | E15: =$B15*(1-E$11) | F15: =$B15*(1-F$11)
A16: Conference table | B16: 46500 | C16: =$B16*(1-C$11) | D16: =$B16*(1-D$11) | E16: =$B16*(1-E$11) | F16: =$B16*(1-F$11)
A18: Challenge: add a 20% column in F11:F16

Sheet S03-03
A1: Salesperson | B1: City | C1: Sales (₹) | D1: Customer Visits | F1: Summary
A2: Amit Joshi | B2: Pune | C2: 485200 | D2: 42 | F2: Average sales
A3: Sneha Kale | B3: Pune | C3: 512750 | D3: 38 | F3: Lowest sales
A4: Rakesh Nair | B4: Mumbai | C4: 638400 | D4: 51 | F4: Highest sales
A5: Fatima Shaikh | B5: Mumbai | C5: 702150 | D5: 47 | F5: Visits entered as numbers
A6: Vivek Deshpande | B6: Nagpur | C6: 356900 | D6: On leave | F6: Entries in the visits column
A7: Pallavi More | B7: Nashik | C7: 298450 | D7: 29 | F7: Blank visit cells
A8: Kiran Salunkhe | B8: Thane | C8: 447600 | D8: 35 | F8: Team size
A9: Manoj Gupta | B9: Thane | C9: 391200 | D9: 33 | F9: Challenge: average visits
A10: Rohit Pawar | B10: Kolhapur | C10: 274300
A11: Swati Kulkarni | B11: Pune | C11: 529800 | D11: 40
A12: Imran Sayyed | B12: Nagpur | C12: 333750 | D12: 31
A13: Neha Agarwal | B13: Mumbai | C13: 584900 | D13: 44
A14: Total

Sheet S03-03 Done
A1: Salesperson | B1: City | C1: Sales (₹) | D1: Customer Visits | F1: Summary
A2: Amit Joshi | B2: Pune | C2: 485200 | D2: 42 | F2: Average sales | G2: =AVERAGE(C2:C13)
A3: Sneha Kale | B3: Pune | C3: 512750 | D3: 38 | F3: Lowest sales | G3: =MIN(C2:C13)
A4: Rakesh Nair | B4: Mumbai | C4: 638400 | D4: 51 | F4: Highest sales | G4: =MAX(C2:C13)
A5: Fatima Shaikh | B5: Mumbai | C5: 702150 | D5: 47 | F5: Visits entered as numbers | G5: =COUNT(D2:D13)
A6: Vivek Deshpande | B6: Nagpur | C6: 356900 | D6: On leave | F6: Entries in the visits column | G6: =COUNTA(D2:D13)
A7: Pallavi More | B7: Nashik | C7: 298450 | D7: 29 | F7: Blank visit cells | G7: =COUNTBLANK(D2:D13)
A8: Kiran Salunkhe | B8: Thane | C8: 447600 | D8: 35 | F8: Team size | G8: =COUNTA(A2:A13)
A9: Manoj Gupta | B9: Thane | C9: 391200 | D9: 33 | F9: Challenge: average visits | G9: =AVERAGE(D2:D13)
A10: Rohit Pawar | B10: Kolhapur | C10: 274300
A11: Swati Kulkarni | B11: Pune | C11: 529800 | D11: 40
A12: Imran Sayyed | B12: Nagpur | C12: 333750 | D12: 31
A13: Neha Agarwal | B13: Mumbai | C13: 584900 | D13: 44
A14: Total | C14: =SUM(C2:C13) | D14: =SUM(D2:D13)

Sheet S03-04
A1: Situation | B1: Value | C1: Formula result | E1: Amount (0 decimals shown) | F1: Rounded with ROUND
A2: GST on ₹12,347 to the nearest rupee (ROUND, 0) | B2: 2222.46 | E2: 10.4
A3: Interest to the nearest paisa (ROUND, 2) | B3: 456.789 | E3: 10.4
A4: Cartons for 250 units, 24 per carton (ROUNDUP) | B4: =250/24 | E4: 10.4
A5: Full cartons you can pack (ROUNDDOWN) | B5: =250/24 | E5: =SUM(E2:E4)
A6: Price to the nearest ₹5 (MROUND) | B6: 487
A7: Price up to the next ₹10 (CEILING) | B7: 487
A8: Price down to the ₹10 below (FLOOR) | B8: 487
A9: Revenue to the nearest lakh (ROUND, -5) | B9: 1234567
A10: Whole years of service (INT) | B10: 7.83
A11: A loss of 7.83 with INT | B11: -7.83
A12: The same loss with TRUNC | B12: -7.83
A13: Challenge: ₹12,34,567 to the nearest thousand | B13: 1234567

Sheet S03-04 Done
A1: Situation | B1: Value | C1: Formula result | E1: Amount (0 decimals shown) | F1: Rounded with ROUND
A2: GST on ₹12,347 to the nearest rupee (ROUND, 0) | B2: 2222.46 | C2: =ROUND(B2,0) | E2: 10.4 | F2: =ROUND(E2,0)
A3: Interest to the nearest paisa (ROUND, 2) | B3: 456.789 | C3: =ROUND(B3,2) | E3: 10.4 | F3: =ROUND(E3,0)
A4: Cartons for 250 units, 24 per carton (ROUNDUP) | B4: =250/24 | C4: =ROUNDUP(B4,0) | E4: 10.4 | F4: =ROUND(E4,0)
A5: Full cartons you can pack (ROUNDDOWN) | B5: =250/24 | C5: =ROUNDDOWN(B5,0) | E5: =SUM(E2:E4) | F5: =SUM(F2:F4)
A6: Price to the nearest ₹5 (MROUND) | B6: 487 | C6: =MROUND(B6,5)
A7: Price up to the next ₹10 (CEILING) | B7: 487 | C7: =CEILING(B7,10)
A8: Price down to the ₹10 below (FLOOR) | B8: 487 | C8: =FLOOR(B8,10)
A9: Revenue to the nearest lakh (ROUND, -5) | B9: 1234567 | C9: =ROUND(B9,-5)
A10: Whole years of service (INT) | B10: 7.83 | C10: =INT(B10)
A11: A loss of 7.83 with INT | B11: -7.83 | C11: =INT(B11)
A12: The same loss with TRUNC | B12: -7.83 | C12: =TRUNC(B12)
A13: Challenge: ₹12,34,567 to the nearest thousand | B13: 1234567 | C13: =ROUND(B13,-3)

Sheet S03-05
A1: Branch | B1: April (linked) | C1: Q1 Total (3-D SUM) | D1: Q1 Target (₹) | E1: Achieved %
A2: Pune
A3: Mumbai
A4: Nashik
A5: Nagpur
A6: Kolhapur
A8: Challenge: Achieved % in E2:E6 = Q1 Total ÷ Q1 Target

Sheet S03-05 Done
A1: Branch | B1: April (linked) | C1: Q1 Total (3-D SUM) | D1: Q1 Target (₹) | E1: Achieved %
A2: Pune | B2: =Apr!B2 | C2: =SUM(Apr:Jun!B2) | D2: ='Targets FY27'!B2 | E2: =C2/D2
A3: Mumbai | B3: =Apr!B3 | C3: =SUM(Apr:Jun!B3) | D3: ='Targets FY27'!B3 | E3: =C3/D3
A4: Nashik | B4: =Apr!B4 | C4: =SUM(Apr:Jun!B4) | D4: ='Targets FY27'!B4 | E4: =C4/D4
A5: Nagpur | B5: =Apr!B5 | C5: =SUM(Apr:Jun!B5) | D5: ='Targets FY27'!B5 | E5: =C5/D5
A6: Kolhapur | B6: =Apr!B6 | C6: =SUM(Apr:Jun!B6) | D6: ='Targets FY27'!B6 | E6: =C6/D6
A8: Challenge: Achieved % in E2:E6 = Q1 Total ÷ Q1 Target

Sheet Apr
A1: Branch | B1: Sales Apr 2026 (₹)
A2: Pune | B2: 1845000
A3: Mumbai | B3: 2612800
A4: Nashik | B4: 965400
A5: Nagpur | B5: 1123600
A6: Kolhapur | B6: 684500

Sheet May
A1: Branch | B1: Sales May 2026 (₹)
A2: Pune | B2: 1762500
A3: Mumbai | B3: 2540300
A4: Nashik | B4: 1012300
A5: Nagpur | B5: 1086900
A6: Kolhapur | B6: 712800

Sheet Jun
A1: Branch | B1: Sales Jun 2026 (₹)
A2: Pune | B2: 1918400
A3: Mumbai | B3: 2787600
A4: Nashik | B4: 988750
A5: Nagpur | B5: 1154200
A6: Kolhapur | B6: 701300

Sheet Targets FY27
A1: Branch | B1: Q1 Target (₹)
A2: Pune | B2: 5600000
A3: Mumbai | B3: 7800000
A4: Nashik | B4: 3000000
A5: Nagpur | B5: 3200000
A6: Kolhapur | B6: 2200000

Sheet S03-06
A1: Item | B1: Taxable Value (₹) | C1: GST (₹) | D1: Total (₹) | F1: GST rate | G1: 0.18
A2: Basmati rice, 25 kg bags | B2: 184000
A3: Assam tea, 1 kg packs | B3: 96500 | E3: Month | F3: North | G3: South | H3: East | I3: West
A4: Garam masala, 200 g | B4: 42300 | E4: Apr | F4: 412000 | G4: 538500 | H4: 296300 | I4: 645800
A5: Turmeric powder, 500 g | B5: 38750 | E5: May | F5: 398750 | G5: 552100 | H5: 301900 | I5: 662400
A6: Cold-pressed groundnut oil, 5 L | B6: 127600 | E6: Jun | F6: 425600 | G6: 561300 | H6: 288700 | I6: 671900
A7: Jaggery cubes, 1 kg | B7: 21400 | E7: Jul | F7: 431200 | G7: 549800 | H7: 310450 | I7: 690300
A8: Challenge: total taxable value | E8: Aug | F8: 447900 | G8: 575600 | H8: 318200 | I8: 702100
E9: Sep | F9: 452300 | G9: 589400 | H9: 325600 | I9: 715800
A10: Zone | B10: Total sales (₹)
A11: North
A12: South
A13: East
A14: West

Sheet S03-06 Done
A1: Item | B1: Taxable Value (₹) | C1: GST (₹) | D1: Total (₹) | F1: GST rate | G1: 0.18
A2: Basmati rice, 25 kg bags | B2: 184000 | C2: =B2*GST_Rate | D2: =B2+C2
A3: Assam tea, 1 kg packs | B3: 96500 | C3: =B3*GST_Rate | D3: =B3+C3 | E3: Month | F3: North | G3: South | H3: East | I3: West
A4: Garam masala, 200 g | B4: 42300 | C4: =B4*GST_Rate | D4: =B4+C4 | E4: Apr | F4: 412000 | G4: 538500 | H4: 296300 | I4: 645800
A5: Turmeric powder, 500 g | B5: 38750 | C5: =B5*GST_Rate | D5: =B5+C5 | E5: May | F5: 398750 | G5: 552100 | H5: 301900 | I5: 662400
A6: Cold-pressed groundnut oil, 5 L | B6: 127600 | C6: =B6*GST_Rate | D6: =B6+C6 | E6: Jun | F6: 425600 | G6: 561300 | H6: 288700 | I6: 671900
A7: Jaggery cubes, 1 kg | B7: 21400 | C7: =B7*GST_Rate | D7: =B7+C7 | E7: Jul | F7: 431200 | G7: 549800 | H7: 310450 | I7: 690300
A8: Challenge: total taxable value | B8: =SUM(Taxable) | E8: Aug | F8: 447900 | G8: 575600 | H8: 318200 | I8: 702100
E9: Sep | F9: 452300 | G9: 589400 | H9: 325600 | I9: 715800
A10: Zone | B10: Total sales (₹)
A11: North | B11: =SUM(North)
A12: South | B12: =SUM(South)
A13: East | B13: =SUM(East)
A14: West | B14: =SUM(West)

Sheet S03-07
A1: Error | B1: Broken formula | C1: Fixed formula | E1: Product | F1: Units | G1: Revenue (₹) | I1: Products A to Z
A2: #DIV/0! | B2: =G2/F2 | E2: Shrikhand 500 g | F2: 0 | G2: 0
A3: #N/A | B3: =_xlfn.XLOOKUP("Ghee 1 L",E2:E6,G2:G6) | E3: Paneer 200 g | F3: 340 | G3: 30600
A4: #NAME? | B4: =SUMM(G2:G6) | E4: Dahi 1 kg | F4: 12 pcs | G4: 1440 | I4: old note
A5: #REF! | B5: =INDEX(G2:G6,7) | E5: Lassi 200 ml | F5: 860 | G5: 21500
A6: #VALUE! | B6: =G4/F4 | E6: Butter 500 g | F6: 210 | G6: 54600
A7: #NUM! | B7: =SQRT(-25)
A8: #CALC!
A10: Challenge: in C11, revenue per unit for Shrikhand (G2/F2), showing 0 instead of an error (IFERROR).
A11: Revenue per unit, Shrikhand

Sheet S03-07 Done
A1: Error | B1: Broken formula | C1: Fixed formula | E1: Product | F1: Units | G1: Revenue (₹) | I1: Products A to Z
A2: #DIV/0! | B2: =G2/F2 | C2: =IF(F2=0,0,G2/F2) | E2: Shrikhand 500 g | F2: 0 | G2: 0 | I2: {=_xlfn._xlws.SORT(E2:E6)}
A3: #N/A | B3: =_xlfn.XLOOKUP("Ghee 1 L",E2:E6,G2:G6) | C3: =_xlfn.XLOOKUP("Ghee 1 L",E2:E6,G2:G6,"Not listed") | E3: Paneer 200 g | F3: 340 | G3: 30600
A4: #NAME? | B4: =SUMM(G2:G6) | C4: =SUM(G2:G6) | E4: Dahi 1 kg | F4: 12 | G4: 1440
A5: #REF! | B5: =INDEX(G2:G6,7) | C5: =INDEX(G2:G6,5) | E5: Lassi 200 ml | F5: 860 | G5: 21500
A6: #VALUE! | B6: =G4/F4 | C6: =G4/F4 | E6: Butter 500 g | F6: 210 | G6: 54600
A7: #NUM! | B7: =SQRT(-25) | C7: =SQRT(25)
A8: #CALC! | B8: {=_xlfn._xlws.FILTER(E2:E6,G2:G6>100000)} | C8: {=_xlfn._xlws.FILTER(E2:E6,G2:G6>100000,"None")}
A10: Challenge: in C11, revenue per unit for Shrikhand (G2/F2), showing 0 instead of an error (IFERROR).
A11: Revenue per unit, Shrikhand | C11: =IFERROR(G2/F2,0)

Sheet S03-08
A1: Item | B1: FY 2026-27 (₹) | D1: Challenge: margin at 20,000 units
A2: Units sold | B2: 18500
A3: Price per unit (₹) | B3: 1450
A4: Revenue | B4: =B2*B3
A5: Cost of goods sold % | B5: 0.62
A6: Cost of goods sold | B6: =B4*B5
A7: Gross profit | B7: =B4-B6
A8: Salaries | B8: 3600000
A9: Rent | B9: 840000
A10: Other expenses | B10: 525000
A11: Total expenses | B11: =B8+B9+450000
A12: Operating profit | B12: =B7-B11
A13: Operating margin | B13: =B12/B4

Sheet S03-08 Done
A1: Item | B1: FY 2026-27 (₹) | D1: Challenge: margin at 20,000 units
A2: Units sold | B2: 18500 | D2: 0.208793
A3: Price per unit (₹) | B3: 1450
A4: Revenue | B4: =B2*B3
A5: Cost of goods sold % | B5: 0.62
A6: Cost of goods sold | B6: =B4*B5
A7: Gross profit | B7: =B4-B6
A8: Salaries | B8: 3600000
A9: Rent | B9: 840000
A10: Other expenses | B10: 525000
A11: Total expenses | B11: =SUM(B8:B10)
A12: Operating profit | B12: =B7-B11
A13: Operating margin | B13: =B12/B4

Sheet S03-09
A1: Profit before bonus (₹) | B1: 2500000 | D1: Check: bonus = rate × profit after bonus
A2: Bonus rate (on profit after bonus) | B2: 0.1 | D2: =B2*B4
A3: Bonus (₹)
A4: Profit after bonus (₹) | B4: =B1-B3
A6: Challenge: bonus if the rate were 12%

Sheet S03-09 Done
A1: Profit before bonus (₹) | B1: 3000000 | D1: Check: bonus = rate × profit after bonus
A2: Bonus rate (on profit after bonus) | B2: 0.1 | D2: =B2*B4
A3: Bonus (₹) | B3: =B1*B2/(1+B2)
A4: Profit after bonus (₹) | B4: =B1-B3
A6: Challenge: bonus if the rate were 12% | B6: =B1*12%/(1+12%)

Sheet S03-10
A1: Salesperson | B1: City | C1: Sales (₹) | D1: Commission (₹) | E1: Commission rounded to ₹10 | G1: Commission rate | H1: 0.025 | J1: Your tasks (Challenge 3)
A2: Amit Joshi | B2: Pune | C2: 487350 | J2: 1. D2: commission = Sales × the rate in H1. Lock H1 with ⌘ + T ($H$1), then fill down to D13.
A3: Sneha Kale | B3: Pune | C3: 512780 | G3: Summary | J3: 2. E2: commission rounded to the nearest ₹10 with MROUND. Fill down to E13.
A4: Rakesh Nair | B4: Mumbai | C4: 638420 | G4: Average sales | J4: 3. Row 14: totals for C, D and E with AutoSum (⌘ + ⇧ + T).
A5: Fatima Shaikh | B5: Mumbai | C5: 702150 | G5: Highest sales | J5: 4. H4:H7: AVERAGE, MAX and MIN of sales, and COUNTA of the names.
A6: Vivek Deshpande | B6: Nagpur | C6: 356960 | G6: Lowest sales | J6: 5. Change the rate in H1 to 3% and check that everything updates. Then set it back to 2.5%.
A7: Pallavi More | B7: Nashik | C7: 298450 | G7: Number of salespeople | J7: Answers: sheet 'S03-10 Answers'.
A8: Kiran Salunkhe | B8: Thane | C8: 447630
A9: Manoj Gupta | B9: Thane | C9: 391240
A10: Rohit Pawar | B10: Kolhapur | C10: 274310
A11: Swati Kulkarni | B11: Pune | C11: 529870
A12: Imran Sayyed | B12: Nagpur | C12: 333750
A13: Neha Agarwal | B13: Mumbai | C13: 584960
A14: Total

Sheet S03-10 Answers
A1: Salesperson | B1: City | C1: Sales (₹) | D1: Commission (₹) | E1: Commission rounded to ₹10 | G1: Commission rate | H1: 0.025 | J1: Your tasks (Challenge 3)
A2: Amit Joshi | B2: Pune | C2: 487350 | D2: =C2*$H$1 | E2: =MROUND(D2,10) | J2: 1. D2: commission = Sales × the rate in H1. Lock H1 with ⌘ + T ($H$1), then fill down to D13.
A3: Sneha Kale | B3: Pune | C3: 512780 | D3: =C3*$H$1 | E3: =MROUND(D3,10) | G3: Summary | J3: 2. E2: commission rounded to the nearest ₹10 with MROUND. Fill down to E13.
A4: Rakesh Nair | B4: Mumbai | C4: 638420 | D4: =C4*$H$1 | E4: =MROUND(D4,10) | G4: Average sales | H4: =AVERAGE(C2:C13) | J4: 3. Row 14: totals for C, D and E with AutoSum (⌘ + ⇧ + T).
A5: Fatima Shaikh | B5: Mumbai | C5: 702150 | D5: =C5*$H$1 | E5: =MROUND(D5,10) | G5: Highest sales | H5: =MAX(C2:C13) | J5: 4. H4:H7: AVERAGE, MAX and MIN of sales, and COUNTA of the names.
A6: Vivek Deshpande | B6: Nagpur | C6: 356960 | D6: =C6*$H$1 | E6: =MROUND(D6,10) | G6: Lowest sales | H6: =MIN(C2:C13) | J6: 5. Change the rate in H1 to 3% and check that everything updates. Then set it back to 2.5%.
A7: Pallavi More | B7: Nashik | C7: 298450 | D7: =C7*$H$1 | E7: =MROUND(D7,10) | G7: Number of salespeople | H7: =COUNTA(A2:A13) | J7: Answers: sheet 'S03-10 Answers'.
A8: Kiran Salunkhe | B8: Thane | C8: 447630 | D8: =C8*$H$1 | E8: =MROUND(D8,10)
A9: Manoj Gupta | B9: Thane | C9: 391240 | D9: =C9*$H$1 | E9: =MROUND(D9,10)
A10: Rohit Pawar | B10: Kolhapur | C10: 274310 | D10: =C10*$H$1 | E10: =MROUND(D10,10)
A11: Swati Kulkarni | B11: Pune | C11: 529870 | D11: =C11*$H$1 | E11: =MROUND(D11,10)
A12: Imran Sayyed | B12: Nagpur | C12: 333750 | D12: =C12*$H$1 | E12: =MROUND(D12,10)
A13: Neha Agarwal | B13: Mumbai | C13: 584960 | D13: =C13*$H$1 | E13: =MROUND(D13,10)
A14: Total | C14: =SUM(C2:C13) | D14: =SUM(D2:D13) | E14: =SUM(E2:E13)
