Workbook

Sheet Start here
A1: S07: Lookups
A2: Excel Mastery for Mac. Practice workbook. Yellow cells are for you to fill in.
A4: Lesson | B4: Title | C4: Type | D4: Practice sheet | E4: Finished sheet
A5: S07-01 | B5: VLOOKUP, exact match | C5: demo | D5: S07-01 | E5: S07-01 Done
A6: S07-02 | B6: Approximate match: commission and discount slabs | C6: demo | D6: S07-02 | E6: S07-02 Done
A7: S07-03 | B7: HLOOKUP, INDEX and MATCH | C7: demo | D7: S07-03 | E7: S07-03 Done
A8: S07-04 | B8: XLOOKUP: the modern lookup | C8: demo | D8: S07-04 | E8: S07-04 Done
A9: S07-05 | B9: XLOOKUP advanced | C9: demo | D9: S07-05 | E9: S07-05 Done
A10: S07-06 | B10: CHOOSE, CHOOSECOLS and CHOOSEROWS | C10: demo | D10: S07-06 | E10: S07-06 Done
A11: S07-07 | B11: INDIRECT, OFFSET, ADDRESS, ROW and COLUMN | C11: demo | D11: S07-07 | E11: S07-07 Done
A12: S07-08 | B12: HYPERLINK and a contents sheet | C12: demo | D12: S07-08 | E12: S07-08 Done
A13: S07-09 | B13: Challenge 5: build an invoice lookup | C13: challenge | D13: S07-09 | E13: S07-09 Answers

Sheet S07-01
A1: Order No | B1: Product Code | C1: Qty | D1: Rate | E1: Amount | F1: GST % | H1: Code | I1: Product | J1: Category | K1: Rate | L1: GST %
A2: SO-2601 | B2: P103 | C2: 4 | E2: =C2*D2 | H2: P104 | I2: Toor Dal 1 kg | J2: Grocery | K2: 165 | L2: 0.05
A3: SO-2602 | B3: P109 | C3: 2 | E3: =C3*D3 | H3: P109 | I3: Ceiling Fan 1200 mm | J3: Electrical | K3: 2890 | L3: 0.18
A4: SO-2603 | B4: P101 | C4: 10 | E4: =C4*D4 | H4: P101 | I4: Assam Tea 1 kg | J4: Beverages | K4: 420 | L4: 0.05
A5: SO-2604 | B5: P108 | C5: 25 | E5: =C5*D5 | H5: P107 | I5: Pressure Cooker 5 L | J5: Home | K5: 2350 | L5: 0.18
A6: SO-2605 | B6: P107 | C6: 1 | E6: =C6*D6 | H6: P103 | I6: Basmati Rice 5 kg | J6: Grocery | K6: 640 | L6: 0.05
A7: SO-2606 | B7: P105 | C7: 12 | E7: =C7*D7 | H7: P110 | I7: Extension Board | J7: Electrical | K7: 549 | L7: 0.18
A8: SO-2607 | B8: P102 | C8: 6 | E8: =C8*D8 | H8: P102 | I8: Coorg Coffee 500 g | J8: Beverages | K8: 380 | L8: 0.05
A9: SO-2608 | B9: P110 | C9: 3 | E9: =C9*D9 | H9: P106 | I9: Steel Bottle 1 L | J9: Home | K9: 450 | L9: 0.18
A10: SO-2609 | B10: P106 | C10: 8 | E10: =C10*D10 | H10: P108 | I10: LED Bulb 9 W | J10: Electrical | K10: 99 | L10: 0.18
A11: SO-2610 | B11: P104 | C11: 15 | E11: =C11*D11 | H11: P105 | I11: Sunflower Oil 1 L | J11: Grocery | K11: 155 | L11: 0.05
A12: SO-2611 | B12: P109 | C12: 1 | E12: =C12*D12
A13: SO-2612 | B13: P111 | C13: 5 | E13: =C13*D13

Sheet S07-01 Done
A1: Order No | B1: Product Code | C1: Qty | D1: Rate | E1: Amount | F1: GST % | H1: Code | I1: Product | J1: Category | K1: Rate | L1: GST %
A2: SO-2601 | B2: P103 | C2: 4 | D2: =VLOOKUP(B2,$H$2:$L$11,4,FALSE) | E2: =C2*D2 | F2: =VLOOKUP(B2,$H$2:$L$11,5,FALSE) | H2: P104 | I2: Toor Dal 1 kg | J2: Grocery | K2: 165 | L2: 0.05
A3: SO-2602 | B3: P109 | C3: 2 | D3: =VLOOKUP(B3,$H$2:$L$11,4,FALSE) | E3: =C3*D3 | F3: =VLOOKUP(B3,$H$2:$L$11,5,FALSE) | H3: P109 | I3: Ceiling Fan 1200 mm | J3: Electrical | K3: 2890 | L3: 0.18
A4: SO-2603 | B4: P101 | C4: 10 | D4: =VLOOKUP(B4,$H$2:$L$11,4,FALSE) | E4: =C4*D4 | F4: =VLOOKUP(B4,$H$2:$L$11,5,FALSE) | H4: P101 | I4: Assam Tea 1 kg | J4: Beverages | K4: 420 | L4: 0.05
A5: SO-2604 | B5: P108 | C5: 25 | D5: =VLOOKUP(B5,$H$2:$L$11,4,FALSE) | E5: =C5*D5 | F5: =VLOOKUP(B5,$H$2:$L$11,5,FALSE) | H5: P107 | I5: Pressure Cooker 5 L | J5: Home | K5: 2350 | L5: 0.18
A6: SO-2605 | B6: P107 | C6: 1 | D6: =VLOOKUP(B6,$H$2:$L$11,4,FALSE) | E6: =C6*D6 | F6: =VLOOKUP(B6,$H$2:$L$11,5,FALSE) | H6: P103 | I6: Basmati Rice 5 kg | J6: Grocery | K6: 640 | L6: 0.05
A7: SO-2606 | B7: P105 | C7: 12 | D7: =VLOOKUP(B7,$H$2:$L$11,4,FALSE) | E7: =C7*D7 | F7: =VLOOKUP(B7,$H$2:$L$11,5,FALSE) | H7: P110 | I7: Extension Board | J7: Electrical | K7: 549 | L7: 0.18
A8: SO-2607 | B8: P102 | C8: 6 | D8: =VLOOKUP(B8,$H$2:$L$11,4,FALSE) | E8: =C8*D8 | F8: =VLOOKUP(B8,$H$2:$L$11,5,FALSE) | H8: P102 | I8: Coorg Coffee 500 g | J8: Beverages | K8: 380 | L8: 0.05
A9: SO-2608 | B9: P110 | C9: 3 | D9: =VLOOKUP(B9,$H$2:$L$11,4,FALSE) | E9: =C9*D9 | F9: =VLOOKUP(B9,$H$2:$L$11,5,FALSE) | H9: P106 | I9: Steel Bottle 1 L | J9: Home | K9: 450 | L9: 0.18
A10: SO-2609 | B10: P106 | C10: 8 | D10: =VLOOKUP(B10,$H$2:$L$11,4,FALSE) | E10: =C10*D10 | F10: =VLOOKUP(B10,$H$2:$L$11,5,FALSE) | H10: P108 | I10: LED Bulb 9 W | J10: Electrical | K10: 99 | L10: 0.18
A11: SO-2610 | B11: P104 | C11: 15 | D11: =VLOOKUP(B11,$H$2:$L$11,4,FALSE) | E11: =C11*D11 | F11: =VLOOKUP(B11,$H$2:$L$11,5,FALSE) | H11: P105 | I11: Sunflower Oil 1 L | J11: Grocery | K11: 155 | L11: 0.05
A12: SO-2611 | B12: P109 | C12: 1 | D12: =VLOOKUP(B12,$H$2:$L$11,4,FALSE) | E12: =C12*D12 | F12: =VLOOKUP(B12,$H$2:$L$11,5,FALSE)
A13: SO-2612 | B13: P111 | C13: 5 | D13: =VLOOKUP(B13,$H$2:$L$11,4,FALSE) | E13: =C13*D13 | F13: =VLOOKUP(B13,$H$2:$L$11,5,FALSE)

Sheet S07-02
A1: Salesperson | B1: Monthly Sales | C1: Rate (VLOOKUP) | D1: Commission | E1: Rate (XLOOKUP) | F1: Slab | H1: Sales From | I1: Rate | J1: Slab
A2: Aarav Sharma | B2: 185000 | D2: =B2*C2 | H2: 0 | I2: 0.02 | J2: Bronze
A3: Priya Nair | B3: 420000 | D3: =B3*C3 | H3: 200000 | I3: 0.03 | J3: Silver
A4: Rohan Mehta | B4: 765000 | D4: =B4*C4 | H4: 500000 | I4: 0.04 | J4: Gold
A5: Sneha Kulkarni | B5: 1240000 | D5: =B5*C5 | H5: 1000000 | I5: 0.05 | J5: Platinum
A6: Vikram Singh | B6: 200000 | D6: =B6*C6 | H6: 2000000 | I6: 0.06 | J6: Diamond
A7: Ananya Iyer | B7: 999000 | D7: =B7*C7
A8: Karthik Reddy | B8: 2150000 | D8: =B8*C8
A9: Meera Joshi | B9: 50000 | D9: =B9*C9
A10: Arjun Patel | B10: 500000 | D10: =B10*C10
A11: Divya Menon | B11: 1575000 | D11: =B11*C11
A12: Farhan Qureshi | B12: 330000 | D12: =B12*C12
A13: Neha Gupta | B13: 45000 | D13: =B13*C13

Sheet S07-02 Done
A1: Salesperson | B1: Monthly Sales | C1: Rate (VLOOKUP) | D1: Commission | E1: Rate (XLOOKUP) | F1: Slab | H1: Sales From | I1: Rate | J1: Slab
A2: Aarav Sharma | B2: 185000 | C2: =VLOOKUP(B2,$H$2:$I$6,2,TRUE) | D2: =B2*C2 | E2: {=_xlfn.XLOOKUP(B2,$H$2:$H$6,$I$2:$I$6,,-1)} | F2: {=_xlfn.XLOOKUP(B2,$H$2:$H$6,$J$2:$J$6,,-1)} | H2: 0 | I2: 0.02 | J2: Bronze
A3: Priya Nair | B3: 420000 | C3: =VLOOKUP(B3,$H$2:$I$6,2,TRUE) | D3: =B3*C3 | E3: {=_xlfn.XLOOKUP(B3,$H$2:$H$6,$I$2:$I$6,,-1)} | F3: {=_xlfn.XLOOKUP(B3,$H$2:$H$6,$J$2:$J$6,,-1)} | H3: 200000 | I3: 0.03 | J3: Silver
A4: Rohan Mehta | B4: 765000 | C4: =VLOOKUP(B4,$H$2:$I$6,2,TRUE) | D4: =B4*C4 | E4: {=_xlfn.XLOOKUP(B4,$H$2:$H$6,$I$2:$I$6,,-1)} | F4: {=_xlfn.XLOOKUP(B4,$H$2:$H$6,$J$2:$J$6,,-1)} | H4: 500000 | I4: 0.04 | J4: Gold
A5: Sneha Kulkarni | B5: 1240000 | C5: =VLOOKUP(B5,$H$2:$I$6,2,TRUE) | D5: =B5*C5 | E5: {=_xlfn.XLOOKUP(B5,$H$2:$H$6,$I$2:$I$6,,-1)} | F5: {=_xlfn.XLOOKUP(B5,$H$2:$H$6,$J$2:$J$6,,-1)} | H5: 1000000 | I5: 0.05 | J5: Platinum
A6: Vikram Singh | B6: 200000 | C6: =VLOOKUP(B6,$H$2:$I$6,2,TRUE) | D6: =B6*C6 | E6: {=_xlfn.XLOOKUP(B6,$H$2:$H$6,$I$2:$I$6,,-1)} | F6: {=_xlfn.XLOOKUP(B6,$H$2:$H$6,$J$2:$J$6,,-1)} | H6: 2000000 | I6: 0.06 | J6: Diamond
A7: Ananya Iyer | B7: 999000 | C7: =VLOOKUP(B7,$H$2:$I$6,2,TRUE) | D7: =B7*C7 | E7: {=_xlfn.XLOOKUP(B7,$H$2:$H$6,$I$2:$I$6,,-1)} | F7: {=_xlfn.XLOOKUP(B7,$H$2:$H$6,$J$2:$J$6,,-1)}
A8: Karthik Reddy | B8: 2150000 | C8: =VLOOKUP(B8,$H$2:$I$6,2,TRUE) | D8: =B8*C8 | E8: {=_xlfn.XLOOKUP(B8,$H$2:$H$6,$I$2:$I$6,,-1)} | F8: {=_xlfn.XLOOKUP(B8,$H$2:$H$6,$J$2:$J$6,,-1)}
A9: Meera Joshi | B9: 50000 | C9: =VLOOKUP(B9,$H$2:$I$6,2,TRUE) | D9: =B9*C9 | E9: {=_xlfn.XLOOKUP(B9,$H$2:$H$6,$I$2:$I$6,,-1)} | F9: {=_xlfn.XLOOKUP(B9,$H$2:$H$6,$J$2:$J$6,,-1)}
A10: Arjun Patel | B10: 500000 | C10: =VLOOKUP(B10,$H$2:$I$6,2,TRUE) | D10: =B10*C10 | E10: {=_xlfn.XLOOKUP(B10,$H$2:$H$6,$I$2:$I$6,,-1)} | F10: {=_xlfn.XLOOKUP(B10,$H$2:$H$6,$J$2:$J$6,,-1)}
A11: Divya Menon | B11: 1575000 | C11: =VLOOKUP(B11,$H$2:$I$6,2,TRUE) | D11: =B11*C11 | E11: {=_xlfn.XLOOKUP(B11,$H$2:$H$6,$I$2:$I$6,,-1)} | F11: {=_xlfn.XLOOKUP(B11,$H$2:$H$6,$J$2:$J$6,,-1)}
A12: Farhan Qureshi | B12: 330000 | C12: =VLOOKUP(B12,$H$2:$I$6,2,TRUE) | D12: =B12*C12 | E12: {=_xlfn.XLOOKUP(B12,$H$2:$H$6,$I$2:$I$6,,-1)} | F12: {=_xlfn.XLOOKUP(B12,$H$2:$H$6,$J$2:$J$6,,-1)}
A13: Neha Gupta | B13: 45000 | C13: =VLOOKUP(B13,$H$2:$I$6,2,TRUE) | D13: =B13*C13 | E13: {=_xlfn.XLOOKUP(B13,$H$2:$H$6,$I$2:$I$6,,-1)} | F13: {=_xlfn.XLOOKUP(B13,$H$2:$H$6,$J$2:$J$6,,-1)}

Sheet S07-03
A1: Region | B1: Apr | C1: May | D1: Jun | E1: Jul | F1: Aug | G1: Sep
A2: North | B2: 194400 | C2: 454700 | D2: 601600 | E2: 616900 | F2: 559800 | G2: 181500 | I2: Month | J2: Jul
A3: South | B3: 594700 | C3: 612100 | D3: 430400 | E3: 271700 | F3: 580100 | G3: 562800 | I3: Region | J3: West
A4: East | B4: 213400 | C4: 236000 | D4: 409000 | E4: 532800 | F4: 259300 | G4: 405500
A5: West | B5: 539300 | C5: 404500 | D5: 555500 | E5: 543800 | F5: 377800 | G5: 507900 | I5: Month total (HLOOKUP)
A6: Central | B6: 482100 | C6: 409100 | D6: 585300 | E6: 543900 | F6: 262000 | G6: 518000 | I6: Region row (MATCH)
A7: Total | B7: =SUM(B2:B6) | C7: =SUM(C2:C6) | D7: =SUM(D2:D6) | E7: =SUM(E2:E6) | F7: =SUM(F2:F6) | G7: =SUM(G2:G6) | I7: Month column (MATCH)
I8: Sales (INDEX + MATCH)
I10: Challenge: region total Apr-Sep

Sheet S07-03 Done
A1: Region | B1: Apr | C1: May | D1: Jun | E1: Jul | F1: Aug | G1: Sep
A2: North | B2: 194400 | C2: 454700 | D2: 601600 | E2: 616900 | F2: 559800 | G2: 181500 | I2: Month | J2: Jul
A3: South | B3: 594700 | C3: 612100 | D3: 430400 | E3: 271700 | F3: 580100 | G3: 562800 | I3: Region | J3: West
A4: East | B4: 213400 | C4: 236000 | D4: 409000 | E4: 532800 | F4: 259300 | G4: 405500
A5: West | B5: 539300 | C5: 404500 | D5: 555500 | E5: 543800 | F5: 377800 | G5: 507900 | I5: Month total (HLOOKUP) | J5: =HLOOKUP(J2,A1:G7,7,FALSE)
A6: Central | B6: 482100 | C6: 409100 | D6: 585300 | E6: 543900 | F6: 262000 | G6: 518000 | I6: Region row (MATCH) | J6: =MATCH(J3,A2:A6,0)
A7: Total | B7: =SUM(B2:B6) | C7: =SUM(C2:C6) | D7: =SUM(D2:D6) | E7: =SUM(E2:E6) | F7: =SUM(F2:F6) | G7: =SUM(G2:G6) | I7: Month column (MATCH) | J7: =MATCH(J2,B1:G1,0)
I8: Sales (INDEX + MATCH) | J8: =INDEX(B2:G6,MATCH(J3,A2:A6,0),MATCH(J2,B1:G1,0))
I10: Challenge: region total Apr-Sep | J10: =SUM(INDEX(B2:G6,MATCH(J3,A2:A6,0),0))

Sheet S07-04
A1: Employee Name | B1: Department | C1: Location | D1: Emp ID | E1: Monthly Salary | G1: Emp ID | H1: EMP1007
A2: Rahul Verma | B2: Finance | C2: Mumbai | D2: EMP1004 | E2: 85000 | G2: Name
A3: Kavya Iyer | B3: HR | C3: Chennai | D3: EMP1011 | E3: 72000 | G3: Monthly salary
A4: Amit Deshpande | B4: Sales | C4: Pune | D4: EMP1001 | E4: 64000
A5: Sana Sheikh | B5: Marketing | C5: Bengaluru | D5: EMP1009 | E5: 91000 | G5: Name, Dept, Location
A6: Harpreet Kaur | B6: Operations | C6: Delhi | D6: EMP1015 | E6: 58000
A7: Nikhil Rao | B7: IT | C7: Hyderabad | D7: EMP1007 | E7: 118000 | G7: Challenge: Emp ID of
A8: Pooja Agarwal | B8: Finance | C8: Kolkata | D8: EMP1002 | E8: 76000 | G8: Kavya Iyer
A9: Suresh Pillai | B9: Sales | C9: Kochi | D9: EMP1013 | E9: 61000
A10: Ishita Bose | B10: IT | C10: Bengaluru | D10: EMP1005 | E10: 104000
A11: Manoj Yadav | B11: Operations | C11: Lucknow | D11: EMP1012 | E11: 55000
A12: Tanvi Shah | B12: Marketing | C12: Ahmedabad | D12: EMP1003 | E12: 83000
A13: Gaurav Malhotra | B13: Sales | C13: Delhi | D13: EMP1010 | E13: 69000
A14: Lakshmi Narayanan | B14: HR | C14: Chennai | D14: EMP1006 | E14: 67000
A15: Deepak Chauhan | B15: IT | C15: Noida | D15: EMP1014 | E15: 97000
A16: Ritu Saxena | B16: Finance | C16: Jaipur | D16: EMP1008 | E16: 88000

Sheet S07-04 Done
A1: Employee Name | B1: Department | C1: Location | D1: Emp ID | E1: Monthly Salary | G1: Emp ID | H1: EMP1007
A2: Rahul Verma | B2: Finance | C2: Mumbai | D2: EMP1004 | E2: 85000 | G2: Name | H2: {=_xlfn.XLOOKUP(H1,D2:D16,A2:A16,"Not found")}
A3: Kavya Iyer | B3: HR | C3: Chennai | D3: EMP1011 | E3: 72000 | G3: Monthly salary | H3: {=_xlfn.XLOOKUP(H1,D2:D16,E2:E16)}
A4: Amit Deshpande | B4: Sales | C4: Pune | D4: EMP1001 | E4: 64000
A5: Sana Sheikh | B5: Marketing | C5: Bengaluru | D5: EMP1009 | E5: 91000 | G5: Name, Dept, Location | H5: {=_xlfn.XLOOKUP(H1,D2:D16,A2:C16)}
A6: Harpreet Kaur | B6: Operations | C6: Delhi | D6: EMP1015 | E6: 58000
A7: Nikhil Rao | B7: IT | C7: Hyderabad | D7: EMP1007 | E7: 118000 | G7: Challenge: Emp ID of
A8: Pooja Agarwal | B8: Finance | C8: Kolkata | D8: EMP1002 | E8: 76000 | G8: Kavya Iyer | H8: {=_xlfn.XLOOKUP(G8,A2:A16,D2:D16,"Not found")}
A9: Suresh Pillai | B9: Sales | C9: Kochi | D9: EMP1013 | E9: 61000
A10: Ishita Bose | B10: IT | C10: Bengaluru | D10: EMP1005 | E10: 104000
A11: Manoj Yadav | B11: Operations | C11: Lucknow | D11: EMP1012 | E11: 55000
A12: Tanvi Shah | B12: Marketing | C12: Ahmedabad | D12: EMP1003 | E12: 83000
A13: Gaurav Malhotra | B13: Sales | C13: Delhi | D13: EMP1010 | E13: 69000
A14: Lakshmi Narayanan | B14: HR | C14: Chennai | D14: EMP1006 | E14: 67000
A15: Deepak Chauhan | B15: IT | C15: Noida | D15: EMP1014 | E15: 97000
A16: Ritu Saxena | B16: Finance | C16: Jaipur | D16: EMP1008 | E16: 88000

Sheet S07-05
A1: Date | B1: Salesperson | C1: Region | D1: Product | E1: Amount | G1: Salesperson | H1: Rohan Mehta
A2: 46114 | B2: Rohan Mehta | C2: West | D2: Ceiling Fan | E2: 28900 | G2: Product | H2: Ceiling Fan
A3: 46117 | B3: Priya Nair | C3: South | D3: LED Bulb 9 W | E3: 4950 | G3: Amount (both match)
A4: 46121 | B4: Aarav Sharma | C4: North | D4: Pressure Cooker | E4: 23500 | G4: Last sale date
A5: 46126 | B5: Rohan Mehta | C5: West | D5: LED Bulb 9 W | E5: 9900 | G5: Product pattern | H5: *Cooker*
A6: 46130 | B6: Sneha Kulkarni | C6: West | D6: Extension Board | E6: 10980 | G6: First amount for pattern
A7: 46134 | B7: Priya Nair | C7: South | D7: Ceiling Fan | E7: 57800 | G7: Row of last sale (XMATCH)
A8: 46139 | B8: Aarav Sharma | C8: North | D8: Steel Bottle | E8: 13500
A9: 46145 | B9: Rohan Mehta | C9: West | D9: Extension Board | E9: 16470 | G9: Challenge: last sale amount of product in H2
A10: 46150 | B10: Sneha Kulkarni | C10: West | D10: Ceiling Fan | E10: 31790
A11: 46154 | B11: Priya Nair | C11: South | D11: Pressure Cooker | E11: 47000
A12: 46158 | B12: Aarav Sharma | C12: North | D12: LED Bulb 9 W | E12: 2970
A13: 46163 | B13: Rohan Mehta | C13: West | D13: Pressure Cooker | E13: 35250
A14: 46168 | B14: Sneha Kulkarni | C14: West | D14: Steel Bottle | E14: 9000
A15: 46171 | B15: Priya Nair | C15: South | D15: Extension Board | E15: 5490
A16: 46173 | B16: Aarav Sharma | C16: North | D16: Ceiling Fan | E16: 40460

Sheet S07-05 Done
A1: Date | B1: Salesperson | C1: Region | D1: Product | E1: Amount | G1: Salesperson | H1: Rohan Mehta
A2: 46114 | B2: Rohan Mehta | C2: West | D2: Ceiling Fan | E2: 28900 | G2: Product | H2: Ceiling Fan
A3: 46117 | B3: Priya Nair | C3: South | D3: LED Bulb 9 W | E3: 4950 | G3: Amount (both match) | H3: {=_xlfn.XLOOKUP(1,(B2:B16=H1)*(D2:D16=H2),E2:E16,"No sale")}
A4: 46121 | B4: Aarav Sharma | C4: North | D4: Pressure Cooker | E4: 23500 | G4: Last sale date | H4: {=_xlfn.XLOOKUP(H1,B2:B16,A2:A16,"None",0,-1)}
A5: 46126 | B5: Rohan Mehta | C5: West | D5: LED Bulb 9 W | E5: 9900 | G5: Product pattern | H5: *Cooker*
A6: 46130 | B6: Sneha Kulkarni | C6: West | D6: Extension Board | E6: 10980 | G6: First amount for pattern | H6: {=_xlfn.XLOOKUP(H5,D2:D16,E2:E16,"No match",2)}
A7: 46134 | B7: Priya Nair | C7: South | D7: Ceiling Fan | E7: 57800 | G7: Row of last sale (XMATCH) | H7: {=_xlfn.XMATCH(H1,B2:B16,0,-1)}
A8: 46139 | B8: Aarav Sharma | C8: North | D8: Steel Bottle | E8: 13500
A9: 46145 | B9: Rohan Mehta | C9: West | D9: Extension Board | E9: 16470 | G9: Challenge: last sale amount of product in H2 | H9: {=_xlfn.XLOOKUP(H2,D2:D16,E2:E16,"None",0,-1)}
A10: 46150 | B10: Sneha Kulkarni | C10: West | D10: Ceiling Fan | E10: 31790
A11: 46154 | B11: Priya Nair | C11: South | D11: Pressure Cooker | E11: 47000
A12: 46158 | B12: Aarav Sharma | C12: North | D12: LED Bulb 9 W | E12: 2970
A13: 46163 | B13: Rohan Mehta | C13: West | D13: Pressure Cooker | E13: 35250
A14: 46168 | B14: Sneha Kulkarni | C14: West | D14: Steel Bottle | E14: 9000
A15: 46171 | B15: Priya Nair | C15: South | D15: Extension Board | E15: 5490
A16: 46173 | B16: Aarav Sharma | C16: North | D16: Ceiling Fan | E16: 40460

Sheet S07-06
A1: Scenario number (1-3) | B1: 2 | D1: Scenarios: 1 Conservative 8%, 2 Base 12%, 3 Optimistic 15%
A2: Scenario
A3: Growth rate
A4: Revenue FY 2025-26 | B4: 12000000
A5: Revenue FY 2026-27 | B5: =B4*(1+B3)
G7: CHOOSECOLS
A8: Branch | B8: Manager | C8: City | D8: Q1 Sales | E8: Q2 Sales
A9: Andheri | B9: Kiran Desai | C9: Mumbai | D9: 4250000 | E9: 4610000
A10: Koramangala | B10: Ramesh Gowda | C10: Bengaluru | D10: 3880000 | E10: 4120000
A11: T Nagar | B11: Lakshmi Srinivasan | C11: Chennai | D11: 2970000 | E11: 3150000
A12: Salt Lake | B12: Arindam Ghosh | C12: Kolkata | D12: 2240000 | E12: 2390000
A13: Connaught Place | B13: Neeraj Kapoor | C13: Delhi | D13: 4560000 | E13: 4390000
A14: Hinjewadi | B14: Sneha Patil | C14: Pune | D14: 3120000 | E14: 3470000
A16: CHOOSEROWS | G16: Challenge

Sheet S07-06 Done
A1: Scenario number (1-3) | B1: 2 | D1: Scenarios: 1 Conservative 8%, 2 Base 12%, 3 Optimistic 15%
A2: Scenario | B2: =CHOOSE(B1,"Conservative","Base","Optimistic")
A3: Growth rate | B3: =CHOOSE(B1,8%,12%,15%)
A4: Revenue FY 2025-26 | B4: 12000000
A5: Revenue FY 2026-27 | B5: =B4*(1+B3)
G7: CHOOSECOLS
A8: Branch | B8: Manager | C8: City | D8: Q1 Sales | E8: Q2 Sales | G8: {=_xlfn.CHOOSECOLS(A8:E14,3,1,5)}
A9: Andheri | B9: Kiran Desai | C9: Mumbai | D9: 4250000 | E9: 4610000
A10: Koramangala | B10: Ramesh Gowda | C10: Bengaluru | D10: 3880000 | E10: 4120000
A11: T Nagar | B11: Lakshmi Srinivasan | C11: Chennai | D11: 2970000 | E11: 3150000
A12: Salt Lake | B12: Arindam Ghosh | C12: Kolkata | D12: 2240000 | E12: 2390000
A13: Connaught Place | B13: Neeraj Kapoor | C13: Delhi | D13: 4560000 | E13: 4390000
A14: Hinjewadi | B14: Sneha Patil | C14: Pune | D14: 3120000 | E14: 3470000
A16: CHOOSEROWS | G16: Challenge
A17: {=_xlfn.CHOOSEROWS(A8:E14,1,-1)} | G17: {=_xlfn.CHOOSECOLS(A8:E14,5,3)}

Sheet S07-07
A1: Branch | B1: Mumbai | D1: Month | E1: Sales | G1: Months with data
A2: Full-year sales | D2: Apr | E2: 1240000 | G2: Last 3 months total
D3: May | E3: 1315000 | G3: Address of last month
A4: Branch sheets: Mumbai, Delhi, Bengaluru | D4: Jun | E4: 1190000
D5: Jul | E5: 1420000 | G5: Challenge: last 3 months with INDEX
D6: Aug | E6: 1365000
D7: Sep | E7: 1510000
D8: Oct
D9: Nov
D10: Dec
D11: Jan
D12: Feb
D13: Mar

Sheet S07-07 Done
A1: Branch | B1: Mumbai | D1: Month | E1: Sales | G1: Months with data | H1: =COUNT(E2:E13)
A2: Full-year sales | B2: =SUM(INDIRECT(B1&"!B2:B13")) | D2: Apr | E2: 1240000 | G2: Last 3 months total | H2: =SUM(OFFSET(E1,H1-2,0,3,1))
D3: May | E3: 1315000 | G3: Address of last month | H3: =ADDRESS(H1+ROW(E1),COLUMN(E1))
A4: Branch sheets: Mumbai, Delhi, Bengaluru | D4: Jun | E4: 1190000
D5: Jul | E5: 1420000 | G5: Challenge: last 3 months with INDEX | H5: =SUM(INDEX(E2:E13,H1-2):INDEX(E2:E13,H1))
D6: Aug | E6: 1365000
D7: Sep | E7: 1510000
D8: Oct
D9: Nov
D10: Dec
D11: Jan
D12: Feb
D13: Mar

Sheet S07-08
A1: Sheet | B1: Link | C1: What it covers
A2: S07-01 | C2: VLOOKUP, exact match
A3: S07-02 | C3: Commission slabs
A4: S07-03 | C4: HLOOKUP, INDEX and MATCH
A5: S07-04 | C5: XLOOKUP basics
A6: S07-05 | C6: XLOOKUP advanced
A7: S07-06 | C7: CHOOSE family
A8: S07-07 | C8: INDIRECT and OFFSET
A10: Website | C10: GST portal
A11: Cell | C11: Rolling 3-month total on S07-07
A13: Back to top | C13: Challenge: link to A1 of this sheet

Sheet S07-08 Done
A1: Sheet | B1: Link | C1: What it covers
A2: S07-01 | B2: =HYPERLINK("#'"&A2&"'!A1","Go to "&A2) | C2: VLOOKUP, exact match
A3: S07-02 | B3: =HYPERLINK("#'"&A3&"'!A1","Go to "&A3) | C3: Commission slabs
A4: S07-03 | B4: =HYPERLINK("#'"&A4&"'!A1","Go to "&A4) | C4: HLOOKUP, INDEX and MATCH
A5: S07-04 | B5: =HYPERLINK("#'"&A5&"'!A1","Go to "&A5) | C5: XLOOKUP basics
A6: S07-05 | B6: =HYPERLINK("#'"&A6&"'!A1","Go to "&A6) | C6: XLOOKUP advanced
A7: S07-06 | B7: =HYPERLINK("#'"&A7&"'!A1","Go to "&A7) | C7: CHOOSE family
A8: S07-07 | B8: =HYPERLINK("#'"&A8&"'!A1","Go to "&A8) | C8: INDIRECT and OFFSET
A10: Website | B10: =HYPERLINK("https://www.gst.gov.in","Open GST portal") | C10: GST portal
A11: Cell | B11: =HYPERLINK("#'S07-07'!H2","Rolling total") | C11: Rolling 3-month total on S07-07
A13: Back to top | B13: =HYPERLINK("#'S07-08 Done'!A1","Back to top") | C13: Challenge: link to A1 of this sheet

Sheet S07-09
A1: TAX INVOICE | J1: Challenge 5: complete the invoice
A2: Invoice No | B2: INV/26-27/0148 | D2: Customer | E2: Shree Ganesh Traders, Pune | J2: 1. In C6, use ONE XLOOKUP to return Product, Rate and GST % for the code in A6
A3: Date | B3: 46318 | D3: GSTIN | E3: 27ABCDE1234F1Z5 | J3: from the 'Product Master' sheet. It should spill into D6 and E6.
J4: 2. If the code is not found, show "Check code".
A5: Code | B5: Qty | C5: Product | D5: Rate | E5: GST % | F5: Taxable Value | G5: GST Amount | H5: Line Total | J5: 3. Copy C6 down to C11.
A6: P103 | B6: 4 | J6: 4. F6: Taxable Value = Qty × Rate
A7: P109 | B7: 2 | J7: 5. G6: GST Amount = Taxable Value × GST %
A8: P101 | B8: 10 | J8: 6. H6: Line Total = Taxable Value + GST Amount. Fill F6:H6 down to row 11.
A9: P108 | B9: 25 | J9: 7. Row 13: SUM the Taxable Value, GST Amount and Line Total columns.
A10: P115 | B10: 3
A11: P106 | B11: 8 | J11: Check: H6 should show ₹2,688.
J12: Answers: sheet 'S07-09 Answers'
E13: Totals

Sheet S07-09 Answers
A1: TAX INVOICE | J1: Challenge 5: complete the invoice
A2: Invoice No | B2: INV/26-27/0148 | D2: Customer | E2: Shree Ganesh Traders, Pune | J2: 1. In C6, use ONE XLOOKUP to return Product, Rate and GST % for the code in A6
A3: Date | B3: 46318 | D3: GSTIN | E3: 27ABCDE1234F1Z5 | J3: from the 'Product Master' sheet. It should spill into D6 and E6.
J4: 2. If the code is not found, show "Check code".
A5: Code | B5: Qty | C5: Product | D5: Rate | E5: GST % | F5: Taxable Value | G5: GST Amount | H5: Line Total | J5: 3. Copy C6 down to C11.
A6: P103 | B6: 4 | C6: {=_xlfn.XLOOKUP(A6,'Product Master'!$A$2:$A$11,'Product Master'!$B$2:$D$11,"Check code")} | F6: =B6*D6 | G6: =F6*E6 | H6: =F6+G6 | J6: 4. F6: Taxable Value = Qty × Rate
A7: P109 | B7: 2 | C7: {=_xlfn.XLOOKUP(A7,'Product Master'!$A$2:$A$11,'Product Master'!$B$2:$D$11,"Check code")} | F7: =B7*D7 | G7: =F7*E7 | H7: =F7+G7 | J7: 5. G6: GST Amount = Taxable Value × GST %
A8: P101 | B8: 10 | C8: {=_xlfn.XLOOKUP(A8,'Product Master'!$A$2:$A$11,'Product Master'!$B$2:$D$11,"Check code")} | F8: =B8*D8 | G8: =F8*E8 | H8: =F8+G8 | J8: 6. H6: Line Total = Taxable Value + GST Amount. Fill F6:H6 down to row 11.
A9: P108 | B9: 25 | C9: {=_xlfn.XLOOKUP(A9,'Product Master'!$A$2:$A$11,'Product Master'!$B$2:$D$11,"Check code")} | F9: =B9*D9 | G9: =F9*E9 | H9: =F9+G9 | J9: 7. Row 13: SUM the Taxable Value, GST Amount and Line Total columns.
A10: P115 | B10: 3 | C10: {=_xlfn.XLOOKUP(A10,'Product Master'!$A$2:$A$11,'Product Master'!$B$2:$D$11,"Check code")} | F10: =B10*D10 | G10: =F10*E10 | H10: =F10+G10
A11: P106 | B11: 8 | C11: {=_xlfn.XLOOKUP(A11,'Product Master'!$A$2:$A$11,'Product Master'!$B$2:$D$11,"Check code")} | F11: =B11*D11 | G11: =F11*E11 | H11: =F11+G11 | J11: Check: H6 should show ₹2,688.
J12: Answers: sheet 'S07-09 Answers'
E13: Totals | F13: =SUM(F6:F11) | G13: =SUM(G6:G11) | H13: =SUM(H6:H11)

Sheet Mumbai
A1: Month | B1: Sales
A2: Apr | B2: 1407500
A3: May | B3: 1578100
A4: Jun | B4: 1272200
A5: Jul | B5: 966800
A6: Aug | B6: 1278300
A7: Sep | B7: 1294500
A8: Oct | B8: 1589600
A9: Nov | B9: 1216000
A10: Dec | B10: 1400900
A11: Jan | B11: 1309900
A12: Feb | B12: 1046800
A13: Mar | B13: 907400
A14: Total | B14: =SUM(B2:B13)

Sheet Delhi
A1: Month | B1: Sales
A2: Apr | B2: 1271800
A3: May | B3: 1414900
A4: Jun | B4: 1445800
A5: Jul | B5: 1175400
A6: Aug | B6: 1148700
A7: Sep | B7: 1392700
A8: Oct | B8: 1137500
A9: Nov | B9: 904800
A10: Dec | B10: 1184400
A11: Jan | B11: 1329700
A12: Feb | B12: 1133500
A13: Mar | B13: 1280600
A14: Total | B14: =SUM(B2:B13)

Sheet Bengaluru
A1: Month | B1: Sales
A2: Apr | B2: 1563900
A3: May | B3: 1565900
A4: Jun | B4: 1230600
A5: Jul | B5: 947800
A6: Aug | B6: 1240300
A7: Sep | B7: 1146800
A8: Oct | B8: 1003600
A9: Nov | B9: 1029900
A10: Dec | B10: 1159800
A11: Jan | B11: 1339100
A12: Feb | B12: 1559100
A13: Mar | B13: 1062600
A14: Total | B14: =SUM(B2:B13)

Sheet Product Master
A1: Code | B1: Product | C1: Rate | D1: GST %
A2: P101 | B2: Assam Tea 1 kg | C2: 420 | D2: 0.05
A3: P102 | B3: Coorg Coffee 500 g | C3: 380 | D3: 0.05
A4: P103 | B4: Basmati Rice 5 kg | C4: 640 | D4: 0.05
A5: P104 | B5: Toor Dal 1 kg | C5: 165 | D5: 0.05
A6: P105 | B6: Sunflower Oil 1 L | C6: 155 | D6: 0.05
A7: P106 | B7: Steel Bottle 1 L | C7: 450 | D7: 0.18
A8: P107 | B8: Pressure Cooker 5 L | C8: 2350 | D8: 0.18
A9: P108 | B9: LED Bulb 9 W | C9: 99 | D9: 0.18
A10: P109 | B10: Ceiling Fan 1200 mm | C10: 2890 | D10: 0.18
A11: P110 | B11: Extension Board | C11: 549 | D11: 0.18
