Workbook

Sheet Start here
A1: Excel Mastery for Mac | Section 12: PivotTables
A2: Practice data: 240 sales invoices of a Pune-based IT hardware distributor, April 2025 to March 2026 (FY 2025-26). Yellow cells are for you to fill. Each lesson builds its PivotTable at a fixed cell on the lesson sheet; the '<id> Done' sheet shows the finished result.
A4: Lesson | B4: Title | C4: Type | D4: Recorded in | E4: Sheet | F4: Finished sheet
A5: S12-01 | B5: Your first PivotTable | C5: demo | D5: Excel for the web | E5: S12-01 | F5: S12-01 Done
A6: S12-02 | B6: Layout and design | C6: demo | D6: Excel desktop | E6: S12-02 | F6: S12-02 Done
A7: S12-03 | B7: Summarise and Show Values As | C7: demo | D7: Excel for the web | E7: S12-03 | F7: S12-03 Done
A8: S12-04 | B8: Grouping dates, numbers and items | C8: demo | D8: Excel desktop | E8: S12-04 | F8: S12-04 Done
A9: S12-05 | B9: Calculated fields and items | C9: demo | D9: Excel desktop | E9: S12-05 | F9: S12-05 Done
A10: S12-06 | B10: Slicers, timelines and report connections | C10: demo | D10: Excel desktop | E10: S12-06 | F10: S12-06 Done
A11: S12-07 | B11: PivotCharts | C11: demo | D11: Excel desktop | E11: S12-07 | F11: S12-07 Done
A12: S12-08 | B12: Refresh, change source, drill down and GETPIVOTDATA | C12: demo | D12: Excel desktop | E12: S12-08 | F12: S12-08 Done
A13: S12-09 | B13: Project: monthly MIS report | C13: project | D13: Excel for the web | E13: S12-09 | F13: S12-09 Done

Sheet S12-01
A1: Date | B1: Invoice No | C1: Region | D1: Branch | E1: Salesperson | F1: Category | G1: Product | H1: Qty | I1: Rate | J1: Sales | K1: Cost | L1: Month | N1: Cross-check: total of Sales column
A2: 45751 | B2: INV/25-26/0001 | C2: East | D2: Kolkata | E2: Sourav Banerjee | F2: Laptops | G2: HP ProBook 440 | H2: 6 | I2: 68000 | J2: 408000 | K2: 336330 | L2: 2025-04
A3: 45751 | B3: INV/25-26/0002 | C3: North | D3: Lucknow | E3: Shalini Tiwari | F3: Printers | G3: Canon PIXMA G3020 | H3: 2 | I3: 14200 | J3: 28400 | K3: 21150 | L3: 2025-04
A4: 45752 | B4: INV/25-26/0003 | C4: East | D4: Bhubaneswar | E4: Ipsita Panda | F4: Laptops | G4: ThinkPad E14 | H4: 3 | I4: 62000 | J4: 186000 | K4: 159400 | L4: 2025-04
A5: 45754 | B5: INV/25-26/0004 | C5: South | D5: Bengaluru | E5: Karthik Rao | F5: Accessories | G5: Seagate 1TB HDD | H5: 11 | I5: 4600 | J5: 50600 | K5: 28210 | L5: 2025-04
A6: 45754 | B6: INV/25-26/0005 | C6: West | D6: Pune | E6: Pooja Joshi | F6: Accessories | G6: Logitech Wireless Combo | H6: 15 | I6: 2400 | J6: 36000 | K6: 21990 | L6: 2025-04
A7: 45755 | B7: INV/25-26/0006 | C7: South | D7: Chennai | E7: Lakshmi Narayanan | F7: Accessories | G7: Logitech Wireless Combo | H7: 29 | I7: 2400 | J7: 69600 | K7: 38300 | L7: 2025-04
A8: 45759 | B8: INV/25-26/0007 | C8: West | D8: Mumbai | E8: Sneha Iyer | F8: Laptops | G8: Dell Latitude 3540 | H8: 6 | I8: 57000 | J8: 342000 | K8: 307670 | L8: 2025-04
A9: 45761 | B9: INV/25-26/0008 | C9: East | D9: Kolkata | E9: Sourav Banerjee | F9: Laptops | G9: HP ProBook 440 | H9: 2 | I9: 68000 | J9: 136000 | K9: 122060 | L9: 2025-04
A10: 45761 | B10: INV/25-26/0009 | C10: North | D10: Lucknow | E10: Aman Srivastava | F10: Accessories | G10: Logitech Wireless Combo | H10: 8 | I10: 2400 | J10: 19200 | K10: 12240 | L10: 2025-04
A11: 45761 | B11: INV/25-26/0010 | C11: North | D11: Delhi | E11: Rohit Malhotra | F11: Laptops | G11: Dell Latitude 3540 | H11: 1 | I11: 57000 | J11: 57000 | K11: 50620 | L11: 2025-04
A12: 45761 | B12: INV/25-26/0011 | C12: West | D12: Mumbai | E12: Rahul Deshmukh | F12: Networking | G12: TP-Link Router AX55 | H12: 8 | I12: 7800 | J12: 62400 | K12: 41530 | L12: 2025-04
A13: 45763 | B13: INV/25-26/0012 | C13: South | D13: Chennai | E13: Lakshmi Narayanan | F13: Networking | G13: D-Link 24-Port Switch | H13: 12 | I13: 15600 | J13: 187200 | K13: 135880 | L13: 2025-04
... A241: 46108 | B241: INV/25-26/0240 | C241: West | D241: Pune | E241: Aditya Kulkarni | F241: Networking | G241: TP-Link Router AX55 | H241: 4 | I241: 7800 | J241: 31200 | K241: 21610 | L241: 2026-03

Sheet S12-01 Done
A1: FINISHED STATE (S12-01): PivotTable on sheet S12-01 at N6. Rows = Region, Columns = Category, Values = Sum of Sales, Filters = Branch (dropdown at N4). N2 cross-check =SUM(J2:J241) equals the grand total.
A6: Sum of Sales / Region | B6: Accessories | C6: Laptops | D6: Networking | E6: Printers | F6: Grand Total
A7: East | B7: 3022000 | C7: 5726000 | D7: 452400 | E7: 813600 | F7: 10014000
A8: North | B8: 2868400 | C8: 4005000 | D8: 1310400 | E8: 915600 | F8: 9099400
A9: South | B9: 2021200 | C9: 3478000 | D9: 1692600 | E9: 396700 | F9: 7588500
A10: West | B10: 3381600 | C10: 3574000 | D10: 1638000 | E10: 540000 | F10: 9133600
A11: Grand Total | B11: 11293200 | C11: 16783000 | D11: 5093400 | E11: 2665900 | F11: 35835500
A13: Challenge answer: Rows = Salesperson, Values = Sum of Qty (sorted largest first)
A14: Salesperson | B14: Sum of Qty
A15: Pooja Joshi | B15: 261
A16: Sourav Banerjee | B16: 207
A17: Shalini Tiwari | B17: 196
A18: Divya Hegde | B18: 183
A19: Sneha Iyer | B19: 178
A20: Rahul Deshmukh | B20: 177
A21: Neha Kapoor | B21: 164
A22: Lakshmi Narayanan | B22: 155
A23: Aman Srivastava | B23: 154
A24: Arun Kumar | B24: 142
A25: Karthik Rao | B25: 121
A26: Sanjay Mohanty | B26: 106
... A30: Aditya Kulkarni | B30: 88

Sheet S12-02
A1: Date | B1: Invoice No | C1: Region | D1: Branch | E1: Salesperson | F1: Category | G1: Product | H1: Qty | I1: Rate | J1: Sales | K1: Cost | L1: Month
A2: 45751 | B2: INV/25-26/0001 | C2: East | D2: Kolkata | E2: Sourav Banerjee | F2: Laptops | G2: HP ProBook 440 | H2: 6 | I2: 68000 | J2: 408000 | K2: 336330 | L2: 2025-04
A3: 45751 | B3: INV/25-26/0002 | C3: North | D3: Lucknow | E3: Shalini Tiwari | F3: Printers | G3: Canon PIXMA G3020 | H3: 2 | I3: 14200 | J3: 28400 | K3: 21150 | L3: 2025-04
A4: 45752 | B4: INV/25-26/0003 | C4: East | D4: Bhubaneswar | E4: Ipsita Panda | F4: Laptops | G4: ThinkPad E14 | H4: 3 | I4: 62000 | J4: 186000 | K4: 159400 | L4: 2025-04
A5: 45754 | B5: INV/25-26/0004 | C5: South | D5: Bengaluru | E5: Karthik Rao | F5: Accessories | G5: Seagate 1TB HDD | H5: 11 | I5: 4600 | J5: 50600 | K5: 28210 | L5: 2025-04
A6: 45754 | B6: INV/25-26/0005 | C6: West | D6: Pune | E6: Pooja Joshi | F6: Accessories | G6: Logitech Wireless Combo | H6: 15 | I6: 2400 | J6: 36000 | K6: 21990 | L6: 2025-04
A7: 45755 | B7: INV/25-26/0006 | C7: South | D7: Chennai | E7: Lakshmi Narayanan | F7: Accessories | G7: Logitech Wireless Combo | H7: 29 | I7: 2400 | J7: 69600 | K7: 38300 | L7: 2025-04
A8: 45759 | B8: INV/25-26/0007 | C8: West | D8: Mumbai | E8: Sneha Iyer | F8: Laptops | G8: Dell Latitude 3540 | H8: 6 | I8: 57000 | J8: 342000 | K8: 307670 | L8: 2025-04
A9: 45761 | B9: INV/25-26/0008 | C9: East | D9: Kolkata | E9: Sourav Banerjee | F9: Laptops | G9: HP ProBook 440 | H9: 2 | I9: 68000 | J9: 136000 | K9: 122060 | L9: 2025-04
A10: 45761 | B10: INV/25-26/0009 | C10: North | D10: Lucknow | E10: Aman Srivastava | F10: Accessories | G10: Logitech Wireless Combo | H10: 8 | I10: 2400 | J10: 19200 | K10: 12240 | L10: 2025-04
A11: 45761 | B11: INV/25-26/0010 | C11: North | D11: Delhi | E11: Rohit Malhotra | F11: Laptops | G11: Dell Latitude 3540 | H11: 1 | I11: 57000 | J11: 57000 | K11: 50620 | L11: 2025-04
A12: 45761 | B12: INV/25-26/0011 | C12: West | D12: Mumbai | E12: Rahul Deshmukh | F12: Networking | G12: TP-Link Router AX55 | H12: 8 | I12: 7800 | J12: 62400 | K12: 41530 | L12: 2025-04
A13: 45763 | B13: INV/25-26/0012 | C13: South | D13: Chennai | E13: Lakshmi Narayanan | F13: Networking | G13: D-Link 24-Port Switch | H13: 12 | I13: 15600 | J13: 187200 | K13: 135880 | L13: 2025-04
... A241: 46108 | B241: INV/25-26/0240 | C241: West | D241: Pune | E241: Aditya Kulkarni | F241: Networking | G241: TP-Link Router AX55 | H241: 4 | I241: 7800 | J241: 31200 | K241: 21610 | L241: 2026-03

Sheet S12-02 Done
A1: FINISHED STATE (S12-02): PivotTable at N6 in Tabular Form, Repeat All Item Labels, no subtotals, banded rows. Rows = Region, Branch. Values = Total Sales (renamed from Sum of Sales, Indian rupee lakh/crore custom format via Number Format) and Sum of Cost. Autofit column widths on update turned off.
A6: Region | B6: Branch | C6: Total Sales | D6: Sum of Cost
A7: East | B7: Bhubaneswar | C7: 4049300 | D7: 3149380
A8: East | B8: Kolkata | C8: 5964700 | D8: 4624740
A9: North | B9: Delhi | C9: 4873600 | D9: 3807100
A10: North | B10: Lucknow | C10: 4225800 | D10: 3074380
A11: South | B11: Bengaluru | C11: 3525500 | D11: 2733040
A12: South | B12: Chennai | C12: 4063000 | D12: 3075610
A13: West | B13: Mumbai | C13: 4338300 | D13: 3298480
A14: West | B14: Pune | C14: 4795300 | D14: 3445980
A15: Grand Total | C15: 35835500 | D15: 27208710
A17: Challenge answer: Report Layout > Show in Outline Form; Subtotals > Show all Subtotals at Top of Group; Blank Rows > Insert Blank Line after Each Item; Sum of Cost > Number Format > Custom (same rupee format).

Sheet S12-03
A1: Date | B1: Invoice No | C1: Region | D1: Branch | E1: Salesperson | F1: Category | G1: Product | H1: Qty | I1: Rate | J1: Sales | K1: Cost | L1: Month
A2: 45751 | B2: INV/25-26/0001 | C2: East | D2: Kolkata | E2: Sourav Banerjee | F2: Laptops | G2: HP ProBook 440 | H2: 6 | I2: 68000 | J2: 408000 | K2: 336330 | L2: 2025-04
A3: 45751 | B3: INV/25-26/0002 | C3: North | D3: Lucknow | E3: Shalini Tiwari | F3: Printers | G3: Canon PIXMA G3020 | H3: 2 | I3: 14200 | J3: 28400 | K3: 21150 | L3: 2025-04
A4: 45752 | B4: INV/25-26/0003 | C4: East | D4: Bhubaneswar | E4: Ipsita Panda | F4: Laptops | G4: ThinkPad E14 | H4: 3 | I4: 62000 | J4: 186000 | K4: 159400 | L4: 2025-04
A5: 45754 | B5: INV/25-26/0004 | C5: South | D5: Bengaluru | E5: Karthik Rao | F5: Accessories | G5: Seagate 1TB HDD | H5: 11 | I5: 4600 | J5: 50600 | K5: 28210 | L5: 2025-04
A6: 45754 | B6: INV/25-26/0005 | C6: West | D6: Pune | E6: Pooja Joshi | F6: Accessories | G6: Logitech Wireless Combo | H6: 15 | I6: 2400 | J6: 36000 | K6: 21990 | L6: 2025-04
A7: 45755 | B7: INV/25-26/0006 | C7: South | D7: Chennai | E7: Lakshmi Narayanan | F7: Accessories | G7: Logitech Wireless Combo | H7: 29 | I7: 2400 | J7: 69600 | K7: 38300 | L7: 2025-04
A8: 45759 | B8: INV/25-26/0007 | C8: West | D8: Mumbai | E8: Sneha Iyer | F8: Laptops | G8: Dell Latitude 3540 | H8: 6 | I8: 57000 | J8: 342000 | K8: 307670 | L8: 2025-04
A9: 45761 | B9: INV/25-26/0008 | C9: East | D9: Kolkata | E9: Sourav Banerjee | F9: Laptops | G9: HP ProBook 440 | H9: 2 | I9: 68000 | J9: 136000 | K9: 122060 | L9: 2025-04
A10: 45761 | B10: INV/25-26/0009 | C10: North | D10: Lucknow | E10: Aman Srivastava | F10: Accessories | G10: Logitech Wireless Combo | H10: 8 | I10: 2400 | J10: 19200 | K10: 12240 | L10: 2025-04
A11: 45761 | B11: INV/25-26/0010 | C11: North | D11: Delhi | E11: Rohit Malhotra | F11: Laptops | G11: Dell Latitude 3540 | H11: 1 | I11: 57000 | J11: 57000 | K11: 50620 | L11: 2025-04
A12: 45761 | B12: INV/25-26/0011 | C12: West | D12: Mumbai | E12: Rahul Deshmukh | F12: Networking | G12: TP-Link Router AX55 | H12: 8 | I12: 7800 | J12: 62400 | K12: 41530 | L12: 2025-04
A13: 45763 | B13: INV/25-26/0012 | C13: South | D13: Chennai | E13: Lakshmi Narayanan | F13: Networking | G13: D-Link 24-Port Switch | H13: 12 | I13: 15600 | J13: 187200 | K13: 135880 | L13: 2025-04
... A241: 46108 | B241: INV/25-26/0240 | C241: West | D241: Pune | E241: Aditya Kulkarni | F241: Networking | G241: TP-Link Router AX55 | H241: 4 | I241: 7800 | J241: 31200 | K241: 21610 | L241: 2026-03

Sheet S12-03 Done
A1: FINISHED STATE (S12-03): PivotTable at N6. Rows = Month. Values = Sum of Sales, Show Values As = Difference From, Base field Month, Base item (previous). Also shown during the lesson: Count, Average, Max, % of Grand Total and Running Total In Month.
A6: Month | B6: Sum of Sales | C6: % of Grand Total | D6: Running Total | E6: Difference From (previous)
A7: 2025-04 | B7: 2732000 | C7: 0.076237251 | D7: 2732000
A8: 2025-05 | B8: 3617000 | C8: 0.10093343 | D8: 6349000 | E8: 885000
A9: 2025-06 | B9: 2785800 | C9: 0.077738555 | D9: 9134800 | E9: -831200
A10: 2025-07 | B10: 4388600 | C10: 0.12246515 | D10: 13523400 | E10: 1602800
A11: 2025-08 | B11: 2753100 | C11: 0.076826052 | D11: 16276500 | E11: -1635500
A12: 2025-09 | B12: 2135400 | C12: 0.059588955 | D12: 18411900 | E12: -617700
A13: 2025-10 | B13: 2404600 | C13: 0.067101059 | D13: 20816500 | E13: 269200
A14: 2025-11 | B14: 2694100 | C14: 0.07517964 | D14: 23510600 | E14: 289500
A15: 2025-12 | B15: 3858600 | C15: 0.10767535 | D15: 27369200 | E15: 1164500
A16: 2026-01 | B16: 2238600 | C16: 0.062468781 | D16: 29607800 | E16: -1620000
A17: 2026-02 | B17: 3922100 | C17: 0.10944734 | D17: 33529900 | E17: 1683500
A18: 2026-03 | B18: 2305600 | C18: 0.064338435 | D18: 35835500 | E18: -1616500
A19: Grand Total | B19: 35835500 | C19: 1
A21: Challenge answer: Rows = Salesperson, Sum of Sales shown as Rank Largest to Smallest
A22: Salesperson | B22: Sum of Sales | C22: Rank
A23: Sourav Banerjee | B23: 3767200 | C23: 1
A24: Pooja Joshi | B24: 2795400 | C24: 2
A25: Rohit Malhotra | B25: 2597800 | C25: 3
A26: Ipsita Panda | B26: 2447500 | C26: 4
A27: Sneha Iyer | B27: 2288900 | C27: 5
A28: Neha Kapoor | B28: 2275800 | C28: 6
A29: Arun Kumar | B29: 2256400 | C29: 7
A30: Shalini Tiwari | B30: 2224100 | C30: 8
A31: Priyanka Das | B31: 2197500 | C31: 9
A32: Rahul Deshmukh | B32: 2049400 | C32: 10
A33: Aman Srivastava | B33: 2001700 | C33: 11
A34: Aditya Kulkarni | B34: 1999900 | C34: 12
... A38: Sanjay Mohanty | B38: 1601800 | C38: 16

Sheet S12-04
A1: Date | B1: Invoice No | C1: Region | D1: Branch | E1: Salesperson | F1: Category | G1: Product | H1: Qty | I1: Rate | J1: Sales | K1: Cost | L1: Month | M1: FY | N1: FY Qtr
A2: 45717 | B2: INV/24-25/0001 | C2: West | D2: Pune | E2: Aditya Kulkarni | F2: Laptops | G2: HP ProBook 440 | H2: 3 | I2: 68000 | J2: 204000 | K2: 177130 | L2: 2025-03
A3: 45719 | B3: INV/24-25/0002 | C3: North | D3: Lucknow | E3: Aman Srivastava | F3: Accessories | G3: Dell 24in Monitor | H3: 10 | I3: 13800 | J3: 138000 | K3: 87330 | L3: 2025-03
A4: 45720 | B4: INV/24-25/0003 | C4: North | D4: Lucknow | E4: Aman Srivastava | F4: Accessories | G4: Logitech Wireless Combo | H4: 19 | I4: 2400 | J4: 45600 | K4: 30370 | L4: 2025-03
A5: 45720 | B5: INV/24-25/0004 | C5: South | D5: Bengaluru | E5: Divya Hegde | F5: Printers | G5: Canon PIXMA G3020 | H5: 6 | I5: 14200 | J5: 85200 | K5: 62730 | L5: 2025-03
A6: 45721 | B6: INV/24-25/0005 | C6: North | D6: Lucknow | E6: Aman Srivastava | F6: Accessories | G6: Seagate 1TB HDD | H6: 9 | I6: 4600 | J6: 41400 | K6: 26550 | L6: 2025-03
A7: 45722 | B7: INV/24-25/0006 | C7: South | D7: Chennai | E7: Lakshmi Narayanan | F7: Laptops | G7: HP ProBook 440 | H7: 3 | I7: 68000 | J7: 204000 | K7: 183430 | L7: 2025-03
A8: 45723 | B8: INV/24-25/0007 | C8: South | D8: Bengaluru | E8: Divya Hegde | F8: Accessories | G8: Logitech Wireless Combo | H8: 19 | I8: 2400 | J8: 45600 | K8: 30700 | L8: 2025-03
A9: 45725 | B9: INV/24-25/0008 | C9: North | D9: Delhi | E9: Neha Kapoor | F9: Laptops | G9: Dell Latitude 3540 | H9: 6 | I9: 57000 | J9: 342000 | K9: 289050 | L9: 2025-03
A10: 45725 | B10: INV/24-25/0009 | C10: West | D10: Mumbai | E10: Sneha Iyer | F10: Laptops | G10: ThinkPad E14 | H10: 2 | I10: 62000 | J10: 124000 | K10: 109070 | L10: 2025-03
A11: 45727 | B11: INV/24-25/0010 | C11: East | D11: Bhubaneswar | E11: Sanjay Mohanty | F11: Accessories | G11: Dell 24in Monitor | H11: 28 | I11: 13800 | J11: 386400 | K11: 225230 | L11: 2025-03
A12: 45727 | B12: INV/24-25/0011 | C12: East | D12: Bhubaneswar | E12: Sanjay Mohanty | F12: Accessories | G12: Logitech Wireless Combo | H12: 14 | I12: 2400 | J12: 33600 | K12: 21640 | L12: 2025-03
A13: 45729 | B13: INV/24-25/0012 | C13: East | D13: Kolkata | E13: Sourav Banerjee | F13: Printers | G13: Canon PIXMA G3020 | H13: 5 | I13: 14200 | J13: 71000 | K13: 58010 | L13: 2025-03
... A261: 46108 | B261: INV/25-26/0240 | C261: West | D261: Pune | E261: Aditya Kulkarni | F261: Networking | G261: TP-Link Router AX55 | H261: 4 | I261: 7800 | J261: 31200 | K261: 21610 | L261: 2026-03

Sheet S12-04 Done
A1: FINISHED STATE (S12-04): Helper columns in the source: M2 ="FY"&(YEAR(A2)+(MONTH(A2)>=4)-1)&"-"&TEXT(MOD(YEAR(A2)+(MONTH(A2)>=4),100),"00") and N2 ="Q"&ROUNDUP((MOD(MONTH(A2)-4,12)+1)/3,0) filled to row 261. PivotTable at P6: Rows = FY, FY Qtr; Values = Sum of Sales. Also built in the lesson: native date grouping (Years/Quarters/Months, calendar based), Sales grouped in bands of 1,00,000 with Count of Invoice No, and a custom group West Metro (Mumbai + Pune).
A6: FY | B6: FY Qtr | C6: Sum of Sales
A7: FY2024-25 | C7: 3253100
B8: Q4 | C8: 3253100
A9: FY2025-26 | C9: 35835500
B10: Q1 | C10: 9134800
B11: Q2 | C11: 9277100
B12: Q3 | C12: 8957300
B13: Q4 | C13: 8466300
A14: Grand Total | C14: 39088600
A16: Sales bands (Starting at 0, Ending at 600000, By 100000)
A17: Sales band | B17: Count of Invoice No
A18: 0-99999 | B18: 121
A19: 100000-199999 | B19: 60
A20: 200000-299999 | B20: 41
A21: 300000-399999 | B21: 24
A22: 400000-499999 | B22: 10
A23: 500000-599999 | B23: 4
A24: Grand Total | B24: 260
A26: Challenge answer: FY2025-26 sales by Branch (rows) and FY Qtr (columns)
A27: Branch | B27: Q1 | C27: Q2 | D27: Q3 | E27: Q4 | F27: Grand Total
A28: Bengaluru | B28: 904300 | C28: 1382200 | D28: 637400 | E28: 601600 | F28: 3525500
A29: Bhubaneswar | B29: 1724400 | C29: 820600 | D29: 930800 | E29: 573500 | F29: 4049300
A30: Chennai | B30: 1156200 | C30: 797000 | D30: 1266000 | E30: 843800 | F30: 4063000
A31: Delhi | B31: 1125000 | C31: 1416600 | D31: 1212800 | E31: 1119200 | F31: 4873600
A32: Kolkata | B32: 1281800 | C32: 962200 | D32: 1838600 | E32: 1882100 | F32: 5964700
A33: Lucknow | B33: 447100 | C33: 1450200 | D33: 939200 | E33: 1389300 | F33: 4225800
A34: Mumbai | B34: 1180600 | C34: 964200 | D34: 985900 | E34: 1207600 | F34: 4338300
A35: Pune | B35: 1315400 | C35: 1484100 | D35: 1146600 | E35: 849200 | F35: 4795300

Sheet S12-05
A1: Date | B1: Invoice No | C1: Region | D1: Branch | E1: Salesperson | F1: Category | G1: Product | H1: Qty | I1: Rate | J1: Sales | K1: Cost | L1: Month | M1: Line Margin %
A2: 45751 | B2: INV/25-26/0001 | C2: East | D2: Kolkata | E2: Sourav Banerjee | F2: Laptops | G2: HP ProBook 440 | H2: 6 | I2: 68000 | J2: 408000 | K2: 336330 | L2: 2025-04 | M2: =(J2-K2)/J2
A3: 45751 | B3: INV/25-26/0002 | C3: North | D3: Lucknow | E3: Shalini Tiwari | F3: Printers | G3: Canon PIXMA G3020 | H3: 2 | I3: 14200 | J3: 28400 | K3: 21150 | L3: 2025-04 | M3: =(J3-K3)/J3
A4: 45752 | B4: INV/25-26/0003 | C4: East | D4: Bhubaneswar | E4: Ipsita Panda | F4: Laptops | G4: ThinkPad E14 | H4: 3 | I4: 62000 | J4: 186000 | K4: 159400 | L4: 2025-04 | M4: =(J4-K4)/J4
A5: 45754 | B5: INV/25-26/0004 | C5: South | D5: Bengaluru | E5: Karthik Rao | F5: Accessories | G5: Seagate 1TB HDD | H5: 11 | I5: 4600 | J5: 50600 | K5: 28210 | L5: 2025-04 | M5: =(J5-K5)/J5
A6: 45754 | B6: INV/25-26/0005 | C6: West | D6: Pune | E6: Pooja Joshi | F6: Accessories | G6: Logitech Wireless Combo | H6: 15 | I6: 2400 | J6: 36000 | K6: 21990 | L6: 2025-04 | M6: =(J6-K6)/J6
A7: 45755 | B7: INV/25-26/0006 | C7: South | D7: Chennai | E7: Lakshmi Narayanan | F7: Accessories | G7: Logitech Wireless Combo | H7: 29 | I7: 2400 | J7: 69600 | K7: 38300 | L7: 2025-04 | M7: =(J7-K7)/J7
A8: 45759 | B8: INV/25-26/0007 | C8: West | D8: Mumbai | E8: Sneha Iyer | F8: Laptops | G8: Dell Latitude 3540 | H8: 6 | I8: 57000 | J8: 342000 | K8: 307670 | L8: 2025-04 | M8: =(J8-K8)/J8
A9: 45761 | B9: INV/25-26/0008 | C9: East | D9: Kolkata | E9: Sourav Banerjee | F9: Laptops | G9: HP ProBook 440 | H9: 2 | I9: 68000 | J9: 136000 | K9: 122060 | L9: 2025-04 | M9: =(J9-K9)/J9
A10: 45761 | B10: INV/25-26/0009 | C10: North | D10: Lucknow | E10: Aman Srivastava | F10: Accessories | G10: Logitech Wireless Combo | H10: 8 | I10: 2400 | J10: 19200 | K10: 12240 | L10: 2025-04 | M10: =(J10-K10)/J10
A11: 45761 | B11: INV/25-26/0010 | C11: North | D11: Delhi | E11: Rohit Malhotra | F11: Laptops | G11: Dell Latitude 3540 | H11: 1 | I11: 57000 | J11: 57000 | K11: 50620 | L11: 2025-04 | M11: =(J11-K11)/J11
A12: 45761 | B12: INV/25-26/0011 | C12: West | D12: Mumbai | E12: Rahul Deshmukh | F12: Networking | G12: TP-Link Router AX55 | H12: 8 | I12: 7800 | J12: 62400 | K12: 41530 | L12: 2025-04 | M12: =(J12-K12)/J12
A13: 45763 | B13: INV/25-26/0012 | C13: South | D13: Chennai | E13: Lakshmi Narayanan | F13: Networking | G13: D-Link 24-Port Switch | H13: 12 | I13: 15600 | J13: 187200 | K13: 135880 | L13: 2025-04 | M13: =(J13-K13)/J13
... A241: 46108 | B241: INV/25-26/0240 | C241: West | D241: Pune | E241: Aditya Kulkarni | F241: Networking | G241: TP-Link Router AX55 | H241: 4 | I241: 7800 | J241: 31200 | K241: 21610 | L241: 2026-03 | M241: =(J241-K241)/J241

Sheet S12-05 Done
A1: FINISHED STATE (S12-05): PivotTable at O6. Rows = Category. Values = Sum of Sales, Sum of Cost and calculated field Margin % = (Sales-Cost)/Sales, Number Format Percentage 1 decimal. The calculated item IT Hardware (=Laptops+Printers) was added to show double counting, then deleted.
A6: Category | B6: Sum of Sales | C6: Sum of Cost | D6: Sum of Margin %
A7: Accessories | B7: 11293200 | C7: 6985760 | D7: 0.38141891
A8: Laptops | B8: 16783000 | C8: 14513130 | D8: 0.13524817
A9: Networking | B9: 5093400 | C9: 3676340 | D9: 0.27821494
A10: Printers | B10: 2665900 | C10: 2033480 | D10: 0.2372257
A11: Grand Total | B11: 35835500 | C11: 27208710 | D11: 0.24073307
A13: Trap shown: Average of Line Margin % (simple average) = 25.4% vs true margin 24.1%
A14: Challenge answer: calculated field Profit = Sales - Cost; highest profit: Accessories (₹43,07,440)

Sheet S12-06
A1: Date | B1: Invoice No | C1: Region | D1: Branch | E1: Salesperson | F1: Category | G1: Product | H1: Qty | I1: Rate | J1: Sales | K1: Cost | L1: Month | N1: Cross-check: South sales (SUMIFS)
A2: 45751 | B2: INV/25-26/0001 | C2: East | D2: Kolkata | E2: Sourav Banerjee | F2: Laptops | G2: HP ProBook 440 | H2: 6 | I2: 68000 | J2: 408000 | K2: 336330 | L2: 2025-04
A3: 45751 | B3: INV/25-26/0002 | C3: North | D3: Lucknow | E3: Shalini Tiwari | F3: Printers | G3: Canon PIXMA G3020 | H3: 2 | I3: 14200 | J3: 28400 | K3: 21150 | L3: 2025-04
A4: 45752 | B4: INV/25-26/0003 | C4: East | D4: Bhubaneswar | E4: Ipsita Panda | F4: Laptops | G4: ThinkPad E14 | H4: 3 | I4: 62000 | J4: 186000 | K4: 159400 | L4: 2025-04
A5: 45754 | B5: INV/25-26/0004 | C5: South | D5: Bengaluru | E5: Karthik Rao | F5: Accessories | G5: Seagate 1TB HDD | H5: 11 | I5: 4600 | J5: 50600 | K5: 28210 | L5: 2025-04
A6: 45754 | B6: INV/25-26/0005 | C6: West | D6: Pune | E6: Pooja Joshi | F6: Accessories | G6: Logitech Wireless Combo | H6: 15 | I6: 2400 | J6: 36000 | K6: 21990 | L6: 2025-04
A7: 45755 | B7: INV/25-26/0006 | C7: South | D7: Chennai | E7: Lakshmi Narayanan | F7: Accessories | G7: Logitech Wireless Combo | H7: 29 | I7: 2400 | J7: 69600 | K7: 38300 | L7: 2025-04
A8: 45759 | B8: INV/25-26/0007 | C8: West | D8: Mumbai | E8: Sneha Iyer | F8: Laptops | G8: Dell Latitude 3540 | H8: 6 | I8: 57000 | J8: 342000 | K8: 307670 | L8: 2025-04
A9: 45761 | B9: INV/25-26/0008 | C9: East | D9: Kolkata | E9: Sourav Banerjee | F9: Laptops | G9: HP ProBook 440 | H9: 2 | I9: 68000 | J9: 136000 | K9: 122060 | L9: 2025-04
A10: 45761 | B10: INV/25-26/0009 | C10: North | D10: Lucknow | E10: Aman Srivastava | F10: Accessories | G10: Logitech Wireless Combo | H10: 8 | I10: 2400 | J10: 19200 | K10: 12240 | L10: 2025-04
A11: 45761 | B11: INV/25-26/0010 | C11: North | D11: Delhi | E11: Rohit Malhotra | F11: Laptops | G11: Dell Latitude 3540 | H11: 1 | I11: 57000 | J11: 57000 | K11: 50620 | L11: 2025-04
A12: 45761 | B12: INV/25-26/0011 | C12: West | D12: Mumbai | E12: Rahul Deshmukh | F12: Networking | G12: TP-Link Router AX55 | H12: 8 | I12: 7800 | J12: 62400 | K12: 41530 | L12: 2025-04
A13: 45763 | B13: INV/25-26/0012 | C13: South | D13: Chennai | E13: Lakshmi Narayanan | F13: Networking | G13: D-Link 24-Port Switch | H13: 12 | I13: 15600 | J13: 187200 | K13: 135880 | L13: 2025-04
... A241: 46108 | B241: INV/25-26/0240 | C241: West | D241: Pune | E241: Aditya Kulkarni | F241: Networking | G241: TP-Link Router AX55 | H241: 4 | I241: 7800 | J241: 31200 | K241: 21610 | L241: 2026-03

Sheet S12-06 Done
A1: FINISHED STATE (S12-06): PivotTable1 at N6 (Rows = Branch, Values = Sum of Sales) and PivotTable2 at N20 (Rows = Category, Values = Sum of Qty). One Region slicer connected to both via Report Connections, South selected. A Date timeline connected to both, June 2025 selected. N2 =SUMIFS(J2:J241,C2:C241,"South").
A6: PivotTable1: Branch | B6: Sum of Sales
A7: Bengaluru | B7: 137000
A8: Chennai | B8: 592800
A9: Grand Total | B9: 729800
A11: PivotTable2: Category | B11: Sum of Qty
A12: Laptops | B12: 9
A13: Networking | B13: 6
A14: Printers | B14: 8
A15: Grand Total | B15: 23
A17: Challenge answer: South, June 2025, Laptops sales = ₹5,46,000

Sheet S12-07
A1: Date | B1: Invoice No | C1: Region | D1: Branch | E1: Salesperson | F1: Category | G1: Product | H1: Qty | I1: Rate | J1: Sales | K1: Cost | L1: Month
A2: 45751 | B2: INV/25-26/0001 | C2: East | D2: Kolkata | E2: Sourav Banerjee | F2: Laptops | G2: HP ProBook 440 | H2: 6 | I2: 68000 | J2: 408000 | K2: 336330 | L2: 2025-04
A3: 45751 | B3: INV/25-26/0002 | C3: North | D3: Lucknow | E3: Shalini Tiwari | F3: Printers | G3: Canon PIXMA G3020 | H3: 2 | I3: 14200 | J3: 28400 | K3: 21150 | L3: 2025-04
A4: 45752 | B4: INV/25-26/0003 | C4: East | D4: Bhubaneswar | E4: Ipsita Panda | F4: Laptops | G4: ThinkPad E14 | H4: 3 | I4: 62000 | J4: 186000 | K4: 159400 | L4: 2025-04
A5: 45754 | B5: INV/25-26/0004 | C5: South | D5: Bengaluru | E5: Karthik Rao | F5: Accessories | G5: Seagate 1TB HDD | H5: 11 | I5: 4600 | J5: 50600 | K5: 28210 | L5: 2025-04
A6: 45754 | B6: INV/25-26/0005 | C6: West | D6: Pune | E6: Pooja Joshi | F6: Accessories | G6: Logitech Wireless Combo | H6: 15 | I6: 2400 | J6: 36000 | K6: 21990 | L6: 2025-04
A7: 45755 | B7: INV/25-26/0006 | C7: South | D7: Chennai | E7: Lakshmi Narayanan | F7: Accessories | G7: Logitech Wireless Combo | H7: 29 | I7: 2400 | J7: 69600 | K7: 38300 | L7: 2025-04
A8: 45759 | B8: INV/25-26/0007 | C8: West | D8: Mumbai | E8: Sneha Iyer | F8: Laptops | G8: Dell Latitude 3540 | H8: 6 | I8: 57000 | J8: 342000 | K8: 307670 | L8: 2025-04
A9: 45761 | B9: INV/25-26/0008 | C9: East | D9: Kolkata | E9: Sourav Banerjee | F9: Laptops | G9: HP ProBook 440 | H9: 2 | I9: 68000 | J9: 136000 | K9: 122060 | L9: 2025-04
A10: 45761 | B10: INV/25-26/0009 | C10: North | D10: Lucknow | E10: Aman Srivastava | F10: Accessories | G10: Logitech Wireless Combo | H10: 8 | I10: 2400 | J10: 19200 | K10: 12240 | L10: 2025-04
A11: 45761 | B11: INV/25-26/0010 | C11: North | D11: Delhi | E11: Rohit Malhotra | F11: Laptops | G11: Dell Latitude 3540 | H11: 1 | I11: 57000 | J11: 57000 | K11: 50620 | L11: 2025-04
A12: 45761 | B12: INV/25-26/0011 | C12: West | D12: Mumbai | E12: Rahul Deshmukh | F12: Networking | G12: TP-Link Router AX55 | H12: 8 | I12: 7800 | J12: 62400 | K12: 41530 | L12: 2025-04
A13: 45763 | B13: INV/25-26/0012 | C13: South | D13: Chennai | E13: Lakshmi Narayanan | F13: Networking | G13: D-Link 24-Port Switch | H13: 12 | I13: 15600 | J13: 187200 | K13: 135880 | L13: 2025-04
... A241: 46108 | B241: INV/25-26/0240 | C241: West | D241: Pune | E241: Aditya Kulkarni | F241: Networking | G241: TP-Link Router AX55 | H241: 4 | I241: 7800 | J241: 31200 | K241: 21610 | L241: 2026-03

Sheet S12-07 Done
A1: FINISHED STATE (S12-07): PivotTable at N6: Rows = Month, Columns = Region, Values = Sum of Sales. PivotChart (Line) titled 'Monthly Sales by Region, FY 2025-26', field buttons hidden. Category slicer set to Laptops filters both chart and pivot. Static values below are the Laptops view.
A6: Month | B6: East | C6: North | D6: South | E6: West | F6: Grand Total
A7: 2025-04 | B7: 1102000 | C7: 568000 | D7: 62000 | E7: 342000 | F7: 2074000
A8: 2025-05 | B8: 476000 | D8: 342000 | E8: 712000 | F8: 1530000
A9: 2025-06 | B9: 458000 | D9: 546000 | E9: 272000 | F9: 1276000
A10: 2025-07 | B10: 693000 | C10: 404000 | D10: 946000 | E10: 747000 | F10: 2790000
A11: 2025-08 | B11: 310000 | C11: 625000 | D11: 114000 | E11: 432000 | F11: 1481000
A12: 2025-09 | B12: 171000 | C12: 186000 | D12: 204000 | F12: 561000
A13: 2025-10 | B13: 340000 | C13: 233000 | D13: 68000 | E13: 124000 | F13: 765000
A14: 2025-11 | B14: 568000 | C14: 478000 | D14: 408000 | E14: 57000 | F14: 1511000
A15: 2025-12 | B15: 780000 | C15: 57000 | D15: 272000 | E15: 402000 | F15: 1511000
A16: 2026-01 | B16: 124000 | C16: 342000 | D16: 114000 | E16: 62000 | F16: 642000
A17: 2026-02 | B17: 456000 | C17: 737000 | D17: 402000 | E17: 248000 | F17: 1843000
A18: 2026-03 | B18: 248000 | C18: 375000 | E18: 176000 | F18: 799000
A19: Grand Total | B19: 5726000 | C19: 4005000 | D19: 3478000 | E19: 3574000 | F19: 16783000
A21: Challenge answer: Printers, October 2025, top region = East (₹1,13,600)

Sheet S12-08
A1: Date | B1: Invoice No | C1: Region | D1: Branch | E1: Salesperson | F1: Category | G1: Product | H1: Qty | I1: Rate | J1: Sales | K1: Cost | L1: Month | N1: Pune sales (GETPIVOTDATA)
A2: 45751 | B2: INV/25-26/0001 | C2: East | D2: Kolkata | E2: Sourav Banerjee | F2: Laptops | G2: HP ProBook 440 | H2: 6 | I2: 68000 | J2: 408000 | K2: 336330 | L2: 2025-04
A3: 45751 | B3: INV/25-26/0002 | C3: North | D3: Lucknow | E3: Shalini Tiwari | F3: Printers | G3: Canon PIXMA G3020 | H3: 2 | I3: 14200 | J3: 28400 | K3: 21150 | L3: 2025-04
A4: 45752 | B4: INV/25-26/0003 | C4: East | D4: Bhubaneswar | E4: Ipsita Panda | F4: Laptops | G4: ThinkPad E14 | H4: 3 | I4: 62000 | J4: 186000 | K4: 159400 | L4: 2025-04
A5: 45754 | B5: INV/25-26/0004 | C5: South | D5: Bengaluru | E5: Karthik Rao | F5: Accessories | G5: Seagate 1TB HDD | H5: 11 | I5: 4600 | J5: 50600 | K5: 28210 | L5: 2025-04
A6: 45754 | B6: INV/25-26/0005 | C6: West | D6: Pune | E6: Pooja Joshi | F6: Accessories | G6: Logitech Wireless Combo | H6: 15 | I6: 2400 | J6: 36000 | K6: 21990 | L6: 2025-04
A7: 45755 | B7: INV/25-26/0006 | C7: South | D7: Chennai | E7: Lakshmi Narayanan | F7: Accessories | G7: Logitech Wireless Combo | H7: 29 | I7: 2400 | J7: 69600 | K7: 38300 | L7: 2025-04
A8: 45759 | B8: INV/25-26/0007 | C8: West | D8: Mumbai | E8: Sneha Iyer | F8: Laptops | G8: Dell Latitude 3540 | H8: 6 | I8: 57000 | J8: 342000 | K8: 307670 | L8: 2025-04
A9: 45761 | B9: INV/25-26/0008 | C9: East | D9: Kolkata | E9: Sourav Banerjee | F9: Laptops | G9: HP ProBook 440 | H9: 2 | I9: 68000 | J9: 136000 | K9: 122060 | L9: 2025-04
A10: 45761 | B10: INV/25-26/0009 | C10: North | D10: Lucknow | E10: Aman Srivastava | F10: Accessories | G10: Logitech Wireless Combo | H10: 8 | I10: 2400 | J10: 19200 | K10: 12240 | L10: 2025-04
A11: 45761 | B11: INV/25-26/0010 | C11: North | D11: Delhi | E11: Rohit Malhotra | F11: Laptops | G11: Dell Latitude 3540 | H11: 1 | I11: 57000 | J11: 57000 | K11: 50620 | L11: 2025-04
A12: 45761 | B12: INV/25-26/0011 | C12: West | D12: Mumbai | E12: Rahul Deshmukh | F12: Networking | G12: TP-Link Router AX55 | H12: 8 | I12: 7800 | J12: 62400 | K12: 41530 | L12: 2025-04
A13: 45763 | B13: INV/25-26/0012 | C13: South | D13: Chennai | E13: Lakshmi Narayanan | F13: Networking | G13: D-Link 24-Port Switch | H13: 12 | I13: 15600 | J13: 187200 | K13: 135880 | L13: 2025-04
... A221: 46081 | B221: INV/25-26/0220 | C221: West | D221: Pune | E221: Pooja Joshi | F221: Networking | G221: D-Link 24-Port Switch | H221: 11 | I221: 15600 | J221: 171600 | K221: 122340 | L221: 2026-02

Sheet S12-08 Done
A1: FINISHED STATE (S12-08): March 2026 rows pasted at A222:L241. PivotTable at N6 (Rows = Branch, Values = Sum of Sales, Filter = Region at N4) with source changed to 'S12-08'!$A$1:$L$241 and refreshed. N2 =GETPIVOTDATA("Sales",$N$6,"Branch","Pune"). Show Report Filter Pages created sheets East, North, South, West.
A6: Branch | B6: Sum of Sales
A7: Bengaluru | B7: 3525500
A8: Bhubaneswar | B8: 4049300
A9: Chennai | B9: 4063000
A10: Delhi | B10: 4873600
A11: Kolkata | B11: 5964700
A12: Lucknow | B12: 4225800
A13: Mumbai | B13: 4338300
A14: Pune | B14: 4795300
A15: Grand Total | B15: 35835500
A17: Before Change Data Source the grand total stayed at ₹3,35,29,900 (April to February only).
A18: Challenge answer: N3 =GETPIVOTDATA("Sales",$N$6,"Branch","Chennai") = ₹40,63,000. With Region = South, the Pune formula shows #REF! because Pune is no longer visible in the pivot.

Sheet S12-08 NewMonth
A1: Date | B1: Invoice No | C1: Region | D1: Branch | E1: Salesperson | F1: Category | G1: Product | H1: Qty | I1: Rate | J1: Sales | K1: Cost | L1: Month
A2: 46085 | B2: INV/25-26/0221 | C2: West | D2: Mumbai | E2: Rahul Deshmukh | F2: Laptops | G2: ThinkPad E14 | H2: 1 | I2: 62000 | J2: 62000 | K2: 54160 | L2: 2026-03
A3: 46086 | B3: INV/25-26/0222 | C3: North | D3: Delhi | E3: Rohit Malhotra | F3: Laptops | G3: HP ProBook 440 | H3: 3 | I3: 68000 | J3: 204000 | K3: 178990 | L3: 2026-03
A4: 46088 | B4: INV/25-26/0223 | C4: West | D4: Pune | E4: Pooja Joshi | F4: Laptops | G4: Dell Latitude 3540 | H4: 2 | I4: 57000 | J4: 114000 | K4: 97190 | L4: 2026-03
A5: 46088 | B5: INV/25-26/0224 | C5: South | D5: Bengaluru | E5: Karthik Rao | F5: Networking | G5: D-Link 24-Port Switch | H5: 7 | I5: 15600 | J5: 109200 | K5: 75030 | L5: 2026-03
A6: 46089 | B6: INV/25-26/0225 | C6: South | D6: Chennai | E6: Arun Kumar | F6: Networking | G6: TP-Link Router AX55 | H6: 10 | I6: 7800 | J6: 78000 | K6: 58190 | L6: 2026-03
A7: 46090 | B7: INV/25-26/0226 | C7: North | D7: Lucknow | E7: Shalini Tiwari | F7: Printers | G7: HP LaserJet M126 | H7: 1 | I7: 18500 | J7: 18500 | K7: 15160 | L7: 2026-03
A8: 46090 | B8: INV/25-26/0227 | C8: North | D8: Delhi | E8: Rohit Malhotra | F8: Laptops | G8: Dell Latitude 3540 | H8: 3 | I8: 57000 | J8: 171000 | K8: 152210 | L8: 2026-03
A9: 46090 | B9: INV/25-26/0228 | C9: North | D9: Lucknow | E9: Aman Srivastava | F9: Accessories | G9: Dell 24in Monitor | H9: 23 | I9: 13800 | J9: 317400 | K9: 196200 | L9: 2026-03
A10: 46093 | B10: INV/25-26/0229 | C10: East | D10: Kolkata | E10: Sourav Banerjee | F10: Accessories | G10: Dell 24in Monitor | H10: 22 | I10: 13800 | J10: 303600 | K10: 175760 | L10: 2026-03
A11: 46096 | B11: INV/25-26/0230 | C11: West | D11: Mumbai | E11: Sneha Iyer | F11: Accessories | G11: Seagate 1TB HDD | H11: 21 | I11: 4600 | J11: 96600 | K11: 63540 | L11: 2026-03
A12: 46097 | B12: INV/25-26/0231 | C12: South | D12: Chennai | E12: Lakshmi Narayanan | F12: Accessories | G12: Seagate 1TB HDD | H12: 17 | I12: 4600 | J12: 78200 | K12: 45070 | L12: 2026-03
A13: 46099 | B13: INV/25-26/0232 | C13: West | D13: Mumbai | E13: Rahul Deshmukh | F13: Networking | G13: TP-Link Router AX55 | H13: 8 | I13: 7800 | J13: 62400 | K13: 45990 | L13: 2026-03
... A21: 46108 | B21: INV/25-26/0240 | C21: West | D21: Pune | E21: Aditya Kulkarni | F21: Networking | G21: TP-Link Router AX55 | H21: 4 | I21: 7800 | J21: 31200 | K21: 21610 | L21: 2026-03

Sheet S12-09
A1: Date | B1: Invoice No | C1: Region | D1: Branch | E1: Salesperson | F1: Category | G1: Product | H1: Qty | I1: Rate | J1: Sales | K1: Cost | L1: Month | M1: Collections
A2: 45751 | B2: INV/25-26/0001 | C2: East | D2: Kolkata | E2: Sourav Banerjee | F2: Laptops | G2: HP ProBook 440 | H2: 6 | I2: 68000 | J2: 408000 | K2: 336330 | L2: 2025-04 | M2: 0
A3: 45751 | B3: INV/25-26/0002 | C3: North | D3: Lucknow | E3: Shalini Tiwari | F3: Printers | G3: Canon PIXMA G3020 | H3: 2 | I3: 14200 | J3: 28400 | K3: 21150 | L3: 2025-04 | M3: 28400
A4: 45752 | B4: INV/25-26/0003 | C4: East | D4: Bhubaneswar | E4: Ipsita Panda | F4: Laptops | G4: ThinkPad E14 | H4: 3 | I4: 62000 | J4: 186000 | K4: 159400 | L4: 2025-04 | M4: 0 | S4: Monthly MIS: branch sales vs target
A5: 45754 | B5: INV/25-26/0004 | C5: South | D5: Bengaluru | E5: Karthik Rao | F5: Accessories | G5: Seagate 1TB HDD | H5: 11 | I5: 4600 | J5: 50600 | K5: 28210 | L5: 2025-04 | M5: 0
A6: 45754 | B6: INV/25-26/0005 | C6: West | D6: Pune | E6: Pooja Joshi | F6: Accessories | G6: Logitech Wireless Combo | H6: 15 | I6: 2400 | J6: 36000 | K6: 21990 | L6: 2025-04 | M6: 36000 | S6: Monthly Target | T6: Achievement % | U6: Collection %
A7: 45755 | B7: INV/25-26/0006 | C7: South | D7: Chennai | E7: Lakshmi Narayanan | F7: Accessories | G7: Logitech Wireless Combo | H7: 29 | I7: 2400 | J7: 69600 | K7: 38300 | L7: 2025-04 | M7: 69600
A8: 45759 | B8: INV/25-26/0007 | C8: West | D8: Mumbai | E8: Sneha Iyer | F8: Laptops | G8: Dell Latitude 3540 | H8: 6 | I8: 57000 | J8: 342000 | K8: 307670 | L8: 2025-04 | M8: 342000
A9: 45761 | B9: INV/25-26/0008 | C9: East | D9: Kolkata | E9: Sourav Banerjee | F9: Laptops | G9: HP ProBook 440 | H9: 2 | I9: 68000 | J9: 136000 | K9: 122060 | L9: 2025-04 | M9: 136000
A10: 45761 | B10: INV/25-26/0009 | C10: North | D10: Lucknow | E10: Aman Srivastava | F10: Accessories | G10: Logitech Wireless Combo | H10: 8 | I10: 2400 | J10: 19200 | K10: 12240 | L10: 2025-04 | M10: 19200
A11: 45761 | B11: INV/25-26/0010 | C11: North | D11: Delhi | E11: Rohit Malhotra | F11: Laptops | G11: Dell Latitude 3540 | H11: 1 | I11: 57000 | J11: 57000 | K11: 50620 | L11: 2025-04 | M11: 57000
A12: 45761 | B12: INV/25-26/0011 | C12: West | D12: Mumbai | E12: Rahul Deshmukh | F12: Networking | G12: TP-Link Router AX55 | H12: 8 | I12: 7800 | J12: 62400 | K12: 41530 | L12: 2025-04 | M12: 15600
A13: 45763 | B13: INV/25-26/0012 | C13: South | D13: Chennai | E13: Lakshmi Narayanan | F13: Networking | G13: D-Link 24-Port Switch | H13: 12 | I13: 15600 | J13: 187200 | K13: 135880 | L13: 2025-04 | M13: 187200
A14: 45763 | B14: INV/25-26/0013 | C14: North | D14: Delhi | E14: Neha Kapoor | F14: Laptops | G14: Dell Latitude 3540 | H14: 3 | I14: 57000 | J14: 171000 | K14: 143490 | L14: 2025-04 | M14: 171000
A15: 45765 | B15: INV/25-26/0014 | C15: East | D15: Bhubaneswar | E15: Sanjay Mohanty | F15: Printers | G15: HP LaserJet M126 | H15: 1 | I15: 18500 | J15: 18500 | K15: 14170 | L15: 2025-04 | M15: 0
A16: 45766 | B16: INV/25-26/0015 | C16: South | D16: Chennai | E16: Lakshmi Narayanan | F16: Networking | G16: D-Link 24-Port Switch | H16: 4 | I16: 15600 | J16: 62400 | K16: 48130 | L16: 2025-04 | M16: 15600
A17: 45766 | B17: INV/25-26/0016 | C17: North | D17: Delhi | E17: Neha Kapoor | F17: Laptops | G17: HP ProBook 440 | H17: 5 | I17: 68000 | J17: 340000 | K17: 297940 | L17: 2025-04 | M17: 0
A18: 45769 | B18: INV/25-26/0017 | C18: West | D18: Pune | E18: Pooja Joshi | F18: Accessories | G18: Logitech Wireless Combo | H18: 13 | I18: 2400 | J18: 31200 | K18: 18400 | L18: 2025-04 | M18: 7800
... A241: 46108 | B241: INV/25-26/0240 | C241: West | D241: Pune | E241: Aditya Kulkarni | F241: Networking | G241: TP-Link Router AX55 | H241: 4 | I241: 7800 | J241: 31200 | K241: 21610 | L241: 2026-03 | M241: 31200

Sheet S12-09 Done
A1: FINISHED STATE (S12-09): PivotTable at P6 on S12-09 in Tabular Form: Rows = Branch, Values = Sum of Sales, Sum of Collections. Month slicer set to 2026-03. S7:S14 =XLOOKUP(P7,'S12-09 Targets'!$A$2:$A$9,'S12-09 Targets'!$B$2:$B$9), T = Sales/Target, U = Collections/Sales, totals in row 15. Exported with File > Export > Download as PDF.
A6: Branch | B6: Sum of Sales | C6: Sum of Collections | D6: Monthly Target | E6: Achievement % | F6: Collection %
A7: Bengaluru | B7: 218400 | C7: 218400 | D7: =_xlfn.XLOOKUP(A7,'S12-09 Targets'!$A$2:$A$9,'S12-09 Targets'!$B$2:$B$9) | E7: =B7/D7 | F7: =C7/B7
A8: Bhubaneswar | B8: 170300 | C8: 87500 | D8: =_xlfn.XLOOKUP(A8,'S12-09 Targets'!$A$2:$A$9,'S12-09 Targets'!$B$2:$B$9) | E8: =B8/D8 | F8: =C8/B8
A9: Chennai | B9: 203000 | C9: 105450 | D9: =_xlfn.XLOOKUP(A9,'S12-09 Targets'!$A$2:$A$9,'S12-09 Targets'!$B$2:$B$9) | E9: =B9/D9 | F9: =C9/B9
A10: Delhi | B10: 460200 | C10: 460200 | D10: =_xlfn.XLOOKUP(A10,'S12-09 Targets'!$A$2:$A$9,'S12-09 Targets'!$B$2:$B$9) | E10: =B10/D10 | F10: =C10/B10
A11: Kolkata | B11: 551600 | C11: 551600 | D11: =_xlfn.XLOOKUP(A11,'S12-09 Targets'!$A$2:$A$9,'S12-09 Targets'!$B$2:$B$9) | E11: =B11/D11 | F11: =C11/B11
A12: Lucknow | B12: 335900 | C12: 256550 | D12: =_xlfn.XLOOKUP(A12,'S12-09 Targets'!$A$2:$A$9,'S12-09 Targets'!$B$2:$B$9) | E12: =B12/D12 | F12: =C12/B12
A13: Mumbai | B13: 221000 | C13: 221000 | D13: =_xlfn.XLOOKUP(A13,'S12-09 Targets'!$A$2:$A$9,'S12-09 Targets'!$B$2:$B$9) | E13: =B13/D13 | F13: =C13/B13
A14: Pune | B14: 145200 | C14: 116700 | D14: =_xlfn.XLOOKUP(A14,'S12-09 Targets'!$A$2:$A$9,'S12-09 Targets'!$B$2:$B$9) | E14: =B14/D14 | F14: =C14/B14
A15: Grand Total | B15: =SUM(B7:B14) | C15: =SUM(C7:C14) | D15: =SUM(D7:D14) | E15: =B15/D15 | F15: =C15/B15
A17: Challenge answer: with the slicer on 2026-02, branches below 100% achievement: Bengaluru, Bhubaneswar, Pune

Sheet S12-09 Targets
A1: Branch | B1: Monthly Target
A2: Bengaluru | B2: 330000
A3: Bhubaneswar | B3: 380000
A4: Chennai | B4: 360000
A5: Delhi | B5: 480000
A6: Kolkata | B6: 530000
A7: Lucknow | B7: 340000
A8: Mumbai | B8: 360000
A9: Pune | B9: 420000
