Workbook

Sheet Start here
A1: S20: AI in Excel 3: Claude in Excel
A2: Excel Mastery for Mac. Practice workbook. Yellow cells are for you to fill in.
A4: Lesson | B4: Type | C4: Title | D4: Practice sheet(s)
A5: S20-01 | B5: concept | C5: Claude in Excel vs Copilot | D5: (whiteboard lesson)
A6: S20-02 | B6: demo | C6: Install and sign in on Mac | D6: S20-02
A7: S20-03 | B7: demo | C7: Understand a workbook you inherited | D7: S20-03, S20-03 Inputs, S20-03 Sales, S20-03 Costs
A8: S20-04 | B8: demo | C8: Find and fix broken formulas | D8: S20-04, S20-04 Inputs, S20-04 Sales, S20-04 Costs
A9: S20-05 | B9: demo | C9: Clean messy data with Claude | D9: S20-05
A10: S20-06 | B10: demo | C10: Build a model from a description | D10: S20-06
A11: S20-07 | B11: demo | C11: Scenarios and sensitivity with Claude | D11: S20-07
A12: S20-08 | B12: demo | C12: From PDF to Excel, and Excel to PowerPoint | D12: S20-08 + data/Sahyadri_Bank_Statement_Sep2026.pdf
A13: S20-09 | B13: concept | C13: Using Claude safely at work | D13: (whiteboard lesson)
A14: S20-10 | B14: demo | C14: Same task, Copilot vs Claude | D14: S20-10, S20-10 Claude
A17: Claude in Excel reads the whole workbook. In prompts, name the sheet you mean (for example: the sheets whose names start with S20-03).
A18: Bank statement PDF for S20-08: data/Sahyadri_Bank_Statement_Sep2026.pdf (sample, fictional bank).

Sheet S20-02
A1: Month | B1: Revenue | C1: Expenses | D1: Profit | E1: Profit margin
A2: 45748 | B2: 1892000 | C2: 1514000 | D2: =B2-C2 | E2: =D2/B2
A3: 45778 | B3: 1939000 | C3: 1566000 | D3: =B3-C3 | E3: =D3/B3
A4: 45809 | B4: 1998000 | C4: 1691000 | D4: =B4-C4 | E4: =D4/B4
A5: 45839 | B5: 1983000 | C5: 1468000 | D5: =B5-C5 | E5: =D5/B5
A6: 45870 | B6: 1956000 | C6: 1568000 | D6: =B6-C6 | E6: =D6/B6
A7: 45901 | B7: 2143000 | C7: 1599000 | D7: =B7-C7 | E7: =D7/B7
A8: 45931 | B8: 2140000 | C8: 1809000 | D8: =B8-C8 | E8: =D8/B8
A9: 45962 | B9: 2024000 | C9: 1501000 | D9: =B9-C9 | E9: =D9/B9
A10: 45992 | B10: 2097000 | C10: 1652000 | D10: =B10-C10 | E10: =D10/B10
A11: 46023 | B11: 2181000 | C11: 1749000 | D11: =B11-C11 | E11: =D11/B11
A12: 46054 | B12: 2272000 | C12: 1790000 | D12: =B12-C12 | E12: =D12/B12
A13: 46082 | B13: 2195000 | C13: 1766000 | D13: =B13-C13 | E13: =D13/B13
A14: FY total | B14: =SUM(B2:B13) | C14: =SUM(C2:C13) | D14: =SUM(D2:D13) | E14: =D14/B14

Sheet S20-02 Done
A1: Month | B1: Revenue | C1: Expenses | D1: Profit | E1: Profit margin | G1: Claude in Excel: ready
A2: 45748 | B2: 1892000 | C2: 1514000 | D2: =B2-C2 | E2: =D2/B2 | G2: ✓ Installed from Microsoft Marketplace (Home > Add-ins)
A3: 45778 | B3: 1939000 | C3: 1566000 | D3: =B3-C3 | E3: =D3/B3 | G3: ✓ Signed in with a paid Claude plan (Pro, Max, Team or Enterprise)
A4: 45809 | B4: 1998000 | C4: 1691000 | D4: =B4-C4 | E4: =D4/B4 | G4: ✓ Open the pane: Control + Option + C on Mac
A5: 45839 | B5: 1983000 | C5: 1468000 | D5: =B5-C5 | E5: =D5/B5 | G5: ✓ Claude reads every sheet and cites cells like D2 or 'S20-03 Sales'!H8
A6: 45870 | B6: 1956000 | C6: 1568000 | D6: =B6-C6 | E6: =D6/B6 | G6: ✓ It asks before larger edits; you approve each one
A7: 45901 | B7: 2143000 | C7: 1599000 | D7: =B7-C7 | E7: =D7/B7
A8: 45931 | B8: 2140000 | C8: 1809000 | D8: =B8-C8 | E8: =D8/B8
A9: 45962 | B9: 2024000 | C9: 1501000 | D9: =B9-C9 | E9: =D9/B9
A10: 45992 | B10: 2097000 | C10: 1652000 | D10: =B10-C10 | E10: =D10/B10
A11: 46023 | B11: 2181000 | C11: 1749000 | D11: =B11-C11 | E11: =D11/B11
A12: 46054 | B12: 2272000 | C12: 1790000 | D12: =B12-C12 | E12: =D12/B12
A13: 46082 | B13: 2195000 | C13: 1766000 | D13: =B13-C13 | E13: =D13/B13
A14: FY total | B14: =SUM(B2:B13) | C14: =SUM(C2:C13) | D14: =SUM(D2:D13) | E14: =D14/B14

Sheet S20-03 Inputs
A1: Assumption | B1: Value | D1: Shree Ganesh Traders, Nagpur. Wholesale rice, oil and dal. FY 2025-26.
A2: COGS % of revenue | B2: 0.78
A3: Monthly rent | B3: 85000
A4: Monthly salaries (Apr to Sep) | B4: 420000
A5: Salary increase from October | B5: 0.08
A6: Other expenses % of revenue | B6: 0.03
A7: Sales commission % of revenue | B7: 0.025

Sheet S20-03 Sales
A1: Month | B1: Basmati rice 25kg (bags) | C1: Rice price | D1: Sunflower oil 15L (tins) | E1: Oil price | F1: Toor dal 30kg (bags) | G1: Dal price | H1: Revenue
A2: 45748 | B2: 1528 | C2: 1850 | D2: 1082 | E2: 2190 | F2: 842 | G2: 3600 | H2: =B2*C2+D2*E2+F2*G2
A3: 45778 | B3: 1556 | C3: 1860 | D3: 972 | E3: 2190 | F3: 778 | G3: 3615 | H3: =B3*C3+D3*E3+F3*G3
A4: 45809 | B4: 1602 | C4: 1870 | D4: 1087 | E4: 2190 | F4: 725 | G4: 3630 | H4: =B4*C4+D4*E4+F4*G4
A5: 45839 | B5: 1542 | C5: 1880 | D5: 986 | E5: 2150 | F5: 774 | G5: 3645 | H5: =B5*C5+D5*E5+F5*G5
A6: 45870 | B6: 1698 | C6: 1890 | D6: 984 | E6: 2190 | F6: 798 | G6: 3660 | H6: =B6*C6+D6*E6+F6*G6
A7: 45901 | B7: 1541 | C7: 1900 | D7: 1029 | E7: 2190 | F7: 802 | G7: 3675 | H7: =B7*C7+D7*E7+F7*G7
A8: 45931 | B8: 2023 | C8: 1910 | D8: 1236 | E8: 2150 | F8: 895 | G8: 3690 | H8: 9786380
A9: 45962 | B9: 1991 | C9: 1920 | D9: 1333 | E9: 2190 | F9: 1021 | G9: 3705 | H9: =B9*C9+D9*E9+F9*G9
A10: 45992 | B10: 1586 | C10: 1930 | D10: 971 | E10: 2190 | F10: 808 | G10: 3720 | H10: =B10*C10+D10*E10+F10*G10
A11: 46023 | B11: 1518 | C11: 1940 | D11: 1029 | E11: 2170 | F11: 786 | G11: 3735 | H11: =B11*C11+D11*E11+F11*G11
A12: 46054 | B12: 1738 | C12: 1950 | D12: 1039 | E12: 2150 | F12: 700 | G12: 3750 | H12: =B12*C12+D12*E12+F12*G12
A13: 46082 | B13: 1716 | C13: 1960 | D13: 982 | E13: 2170 | F13: 766 | G13: 3765 | H13: =B13*C13+D13*E13+F13*G13

Sheet S20-03 Costs
A1: Month | B1: COGS | C1: Salaries | D1: Rent | E1: Commission | F1: Other expenses
A2: 45748 | B2: ='S20-03 Sales'!H2*'S20-03 Inputs'!$B$2 | C2: ='S20-03 Inputs'!$B$4 | D2: ='S20-03 Inputs'!$B$3 | E2: ='S20-03 Sales'!H2*'S20-03 Inputs'!B7 | F2: ='S20-03 Sales'!H2*'S20-03 Inputs'!$B$6
A3: 45778 | B3: ='S20-03 Sales'!H3*'S20-03 Inputs'!$B$2 | C3: ='S20-03 Inputs'!$B$4 | D3: ='S20-03 Inputs'!$B$3 | E3: ='S20-03 Sales'!H3*'S20-03 Inputs'!B8 | F3: ='S20-03 Sales'!H3*'S20-03 Inputs'!$B$6
A4: 45809 | B4: ='S20-03 Sales'!H4*'S20-03 Inputs'!$B$2 | C4: ='S20-03 Inputs'!$B$4 | D4: ='S20-03 Inputs'!$B$3 | E4: ='S20-03 Sales'!H4*'S20-03 Inputs'!B9 | F4: ='S20-03 Sales'!H4*'S20-03 Inputs'!$B$6
A5: 45839 | B5: ='S20-03 Sales'!H5*'S20-03 Inputs'!$B$2 | C5: ='S20-03 Inputs'!$B$4 | D5: ='S20-03 Inputs'!$B$3 | E5: ='S20-03 Sales'!H5*'S20-03 Inputs'!B10 | F5: ='S20-03 Sales'!H5*'S20-03 Inputs'!$B$6
A6: 45870 | B6: ='S20-03 Sales'!H6*'S20-03 Inputs'!$B$2 | C6: ='S20-03 Inputs'!$B$4 | D6: ='S20-03 Inputs'!$B$3 | E6: ='S20-03 Sales'!H6*'S20-03 Inputs'!B11 | F6: ='S20-03 Sales'!H6*'S20-03 Inputs'!$B$6
A7: 45901 | B7: ='S20-03 Sales'!H7*'S20-03 Inputs'!$B$2 | C7: ='S20-03 Inputs'!$B$4 | D7: ='S20-03 Inputs'!$B$3 | E7: ='S20-03 Sales'!H7*'S20-03 Inputs'!B12 | F7: ='S20-03 Sales'!H7*'S20-03 Inputs'!$B$6
A8: 45931 | B8: ='S20-03 Sales'!H8*'S20-03 Inputs'!$B$2 | C8: ='S20-03 Inputs'!$B$4*(1+'S20-03 Inputs'!$B$5) | D8: ='S20-03 Inputs'!$B$3 | E8: ='S20-03 Sales'!H8*'S20-03 Inputs'!B13 | F8: ='S20-03 Sales'!H8*'S20-03 Inputs'!$B$6
A9: 45962 | B9: ='S20-03 Sales'!H9*'S20-03 Inputs'!$B$2 | C9: ='S20-03 Inputs'!$B$4*(1+'S20-03 Inputs'!$B$5) | D9: ='S20-03 Inputs'!$B$3 | E9: ='S20-03 Sales'!H9*'S20-03 Inputs'!B14 | F9: ='S20-03 Sales'!H9*'S20-03 Inputs'!$B$6
A10: 45992 | B10: ='S20-03 Sales'!H10*'S20-03 Inputs'!$B$2 | C10: ='S20-03 Inputs'!$B$4*(1+'S20-03 Inputs'!$B$5) | D10: ='S20-03 Inputs'!$B$3 | E10: ='S20-03 Sales'!H10*'S20-03 Inputs'!B15 | F10: ='S20-03 Sales'!H10*'S20-03 Inputs'!$B$6
A11: 46023 | B11: ='S20-03 Sales'!H11*'S20-03 Inputs'!$B$2 | C11: ='S20-03 Inputs'!$B$4*(1+'S20-03 Inputs'!$B$5) | D11: ='S20-03 Inputs'!$B$3 | E11: ='S20-03 Sales'!H11*'S20-03 Inputs'!B16 | F11: ='S20-03 Sales'!H11*'S20-03 Inputs'!$B$6
A12: 46054 | B12: ='S20-03 Sales'!H12*'S20-03 Inputs'!$B$2 | C12: ='S20-03 Inputs'!$B$4*(1+'S20-03 Inputs'!$B$5) | D12: ='S20-03 Inputs'!$B$3 | E12: ='S20-03 Sales'!H12*'S20-03 Inputs'!B17 | F12: ='S20-03 Sales'!H12*'S20-03 Inputs'!$B$6
A13: 46082 | B13: ='S20-03 Sales'!H13*'S20-03 Inputs'!$B$2 | C13: ='S20-03 Inputs'!$B$4*(1+'S20-03 Inputs'!$B$5) | D13: ='S20-03 Inputs'!$B$3 | E13: ='S20-03 Sales'!H13*'S20-03 Inputs'!B18 | F13: ='S20-03 Sales'!H13*'S20-03 Inputs'!$B$6

Sheet S20-03
A1: Line item | B1: Apr-25 | C1: May-25 | D1: Jun-25 | E1: Jul-25 | F1: Aug-25 | G1: Sep-25 | H1: Oct-25 | I1: Nov-25 | J1: Dec-25 | K1: Jan-26 | L1: Feb-26 | M1: Mar-26 | N1: FY total
A2: Revenue | B2: ='S20-03 Sales'!H2 | C2: ='S20-03 Sales'!H3 | D2: ='S20-03 Sales'!H4 | E2: ='S20-03 Sales'!H5 | F2: ='S20-03 Sales'!H6 | G2: ='S20-03 Sales'!H7 | H2: ='S20-03 Sales'!H8 | I2: ='S20-03 Sales'!H9 | J2: ='S20-03 Sales'!H10 | K2: ='S20-03 Sales'!H11 | L2: ='S20-03 Sales'!H12 | M2: ='S20-03 Sales'!H13 | N2: =SUM(B2:M2)
A3: COGS | B3: ='S20-03 Costs'!B2 | C3: ='S20-03 Costs'!B3 | D3: ='S20-03 Costs'!B4 | E3: ='S20-03 Costs'!B5 | F3: ='S20-03 Costs'!B6 | G3: ='S20-03 Costs'!B7 | H3: ='S20-03 Costs'!B8 | I3: ='S20-03 Costs'!B9 | J3: ='S20-03 Costs'!B10 | K3: ='S20-03 Costs'!B11 | L3: ='S20-03 Costs'!B12 | M3: ='S20-03 Costs'!B13 | N3: =SUM(B3:M3)
A4: Gross profit | B4: =B2-B3 | C4: =C2-C3 | D4: =D2-D3 | E4: =E2-E3 | F4: =F2-F3 | G4: =G2-G3 | H4: =H2-H3 | I4: =I2-I3 | ... M4: =M2-M3 | N4: =SUM(B4:M4)
A5: Gross margin % | B5: =B4/B2 | C5: =C4/C2 | D5: =D4/D2 | E5: =E4/E2 | F5: =F4/F2 | G5: =G4/G2 | H5: =H4/H2 | I5: =I4/I2 | ... N5: =N4/N2
A6: Salaries | B6: ='S20-03 Costs'!C2 | C6: ='S20-03 Costs'!C3 | D6: ='S20-03 Costs'!C4 | E6: ='S20-03 Costs'!C5 | F6: ='S20-03 Costs'!C6 | G6: ='S20-03 Costs'!C7 | H6: ='S20-03 Costs'!C8 | I6: ='S20-03 Costs'!C9 | J6: ='S20-03 Costs'!C10 | K6: ='S20-03 Costs'!C11 | L6: ='S20-03 Costs'!C12 | M6: ='S20-03 Costs'!C13 | N6: =SUM(B6:M6)
A7: Rent | B7: ='S20-03 Costs'!D2 | C7: ='S20-03 Costs'!D3 | D7: ='S20-03 Costs'!D4 | E7: ='S20-03 Costs'!D5 | F7: ='S20-03 Costs'!D6 | G7: ='S20-03 Costs'!D7 | H7: ='S20-03 Costs'!D8 | I7: ='S20-03 Costs'!D9 | J7: ='S20-03 Costs'!D10 | K7: ='S20-03 Costs'!D11 | L7: ='S20-03 Costs'!D12 | M7: ='S20-03 Costs'!D13 | N7: =SUM(B7:M7)
A8: Commission | B8: ='S20-03 Costs'!E2 | C8: ='S20-03 Costs'!E3 | D8: ='S20-03 Costs'!E4 | E8: ='S20-03 Costs'!E5 | F8: ='S20-03 Costs'!E6 | G8: ='S20-03 Costs'!E7 | H8: ='S20-03 Costs'!E8 | I8: ='S20-03 Costs'!E9 | J8: ='S20-03 Costs'!E10 | K8: ='S20-03 Costs'!E11 | L8: ='S20-03 Costs'!E12 | M8: ='S20-03 Costs'!E13 | N8: =SUM(B8:M8)
A9: Other expenses | B9: ='S20-03 Costs'!F2 | C9: ='S20-03 Costs'!F3 | D9: ='S20-03 Costs'!F4 | E9: ='S20-03 Costs'!#REF! | F9: ='S20-03 Costs'!F6 | G9: ='S20-03 Costs'!F7 | H9: ='S20-03 Costs'!F8 | I9: ='S20-03 Costs'!F9 | J9: ='S20-03 Costs'!F10 | K9: ='S20-03 Costs'!F11 | L9: ='S20-03 Costs'!F12 | M9: ='S20-03 Costs'!F13 | N9: =SUM(B9:M9)
A10: Total operating expenses | B10: =SUM(B6:B9) | C10: =SUM(C6:C9) | D10: =SUM(D6:D9) | E10: =SUM(E6:E9) | F10: =SUM(F6:F9) | G10: =SUM(G6:G9) | H10: =SUM(H6:H9) | I10: =SUM(I6:I9) | ... M10: =SUM(M6:M9) | N10: =SUM(B10:M10)
A11: EBITDA | B11: =B4-B10 | C11: =C4-C10 | D11: =D4-D10 | E11: =E4-E10 | F11: =F4-F10 | G11: =G4-G10 | H11: =H4-H10 | I11: =I4-I10 | ... M11: =M4-M10 | N11: =SUM(B11:L11)
A12: EBITDA margin % | B12: =B11/B2 | C12: =C11/C2 | D12: =D11/D2 | E12: =E11/E2 | F12: =F11/F2 | G12: =G11/G2 | H12: =H11/H2 | I12: =I11/I2 | ... N12: =N11/N2
A15: Hand check: revenue from the Sales sheet

Sheet S20-03 Done
A1: How the inherited workbook fits together (map written with Claude, checked by hand)
A3: Step | B3: Sheet | C3: What it holds | D3: Feeds into | E3: Key cells
A4: 1 | B4: S20-03 Inputs | C4: Assumptions: COGS %, rent, salaries, increment, other %, commission % | D4: S20-03 Costs | E4: B2:B7
A5: 2 | B5: S20-03 Sales | C5: Units x price for rice, oil and dal by month | D5: S20-03 Costs, S20-03 | E5: H2:H13 = Revenue
A6: 3 | B6: S20-03 Costs | C6: COGS, salaries, rent, commission, other expenses by month | D6: S20-03 | E6: B2:F13
A7: 4 | B7: S20-03 | C7: Monthly P&L summary and FY totals | D7: Reports | E7: N2 Revenue, N11 EBITDA
A9: ! | B9: Spotted on the way | C9: H8 in Sales is a typed number; Costs E3:E13 commission is 0; summary E9 is #REF!; N11 misses March | D9: Fix in S20-04
A12: Flow: Inputs → Sales → Costs → Summary (S20-03)

Sheet S20-04 Inputs
A1: Assumption | B1: Value | D1: Shree Ganesh Traders, Nagpur. Wholesale rice, oil and dal. FY 2025-26.
A2: COGS % of revenue | B2: 0.78
A3: Monthly rent | B3: 85000
A4: Monthly salaries (Apr to Sep) | B4: 420000
A5: Salary increase from October | B5: 0.08
A6: Other expenses % of revenue | B6: 0.03
A7: Sales commission % of revenue | B7: 0.025

Sheet S20-04 Sales
A1: Month | B1: Basmati rice 25kg (bags) | C1: Rice price | D1: Sunflower oil 15L (tins) | E1: Oil price | F1: Toor dal 30kg (bags) | G1: Dal price | H1: Revenue
A2: 45748 | B2: 1528 | C2: 1850 | D2: 1082 | E2: 2190 | F2: 842 | G2: 3600 | H2: =B2*C2+D2*E2+F2*G2
A3: 45778 | B3: 1556 | C3: 1860 | D3: 972 | E3: 2190 | F3: 778 | G3: 3615 | H3: =B3*C3+D3*E3+F3*G3
A4: 45809 | B4: 1602 | C4: 1870 | D4: 1087 | E4: 2190 | F4: 725 | G4: 3630 | H4: =B4*C4+D4*E4+F4*G4
A5: 45839 | B5: 1542 | C5: 1880 | D5: 986 | E5: 2150 | F5: 774 | G5: 3645 | H5: =B5*C5+D5*E5+F5*G5
A6: 45870 | B6: 1698 | C6: 1890 | D6: 984 | E6: 2190 | F6: 798 | G6: 3660 | H6: =B6*C6+D6*E6+F6*G6
A7: 45901 | B7: 1541 | C7: 1900 | D7: 1029 | E7: 2190 | F7: 802 | G7: 3675 | H7: =B7*C7+D7*E7+F7*G7
A8: 45931 | B8: 2023 | C8: 1910 | D8: 1236 | E8: 2150 | F8: 895 | G8: 3690 | H8: 9786380
A9: 45962 | B9: 1991 | C9: 1920 | D9: 1333 | E9: 2190 | F9: 1021 | G9: 3705 | H9: =B9*C9+D9*E9+F9*G9
A10: 45992 | B10: 1586 | C10: 1930 | D10: 971 | E10: 2190 | F10: 808 | G10: 3720 | H10: =B10*C10+D10*E10+F10*G10
A11: 46023 | B11: 1518 | C11: 1940 | D11: 1029 | E11: 2170 | F11: 786 | G11: 3735 | H11: =B11*C11+D11*E11+F11*G11
A12: 46054 | B12: 1738 | C12: 1950 | D12: 1039 | E12: 2150 | F12: 700 | G12: 3750 | H12: =B12*C12+D12*E12+F12*G12
A13: 46082 | B13: 1716 | C13: 1960 | D13: 982 | E13: 2170 | F13: 766 | G13: 3765 | H13: =B13*C13+D13*E13+F13*G13

Sheet S20-04 Costs
A1: Month | B1: COGS | C1: Salaries | D1: Rent | E1: Commission | F1: Other expenses
A2: 45748 | B2: ='S20-04 Sales'!H2*'S20-04 Inputs'!$B$2 | C2: ='S20-04 Inputs'!$B$4 | D2: ='S20-04 Inputs'!$B$3 | E2: ='S20-04 Sales'!H2*'S20-04 Inputs'!B7 | F2: ='S20-04 Sales'!H2*'S20-04 Inputs'!$B$6
A3: 45778 | B3: ='S20-04 Sales'!H3*'S20-04 Inputs'!$B$2 | C3: ='S20-04 Inputs'!$B$4 | D3: ='S20-04 Inputs'!$B$3 | E3: ='S20-04 Sales'!H3*'S20-04 Inputs'!B8 | F3: ='S20-04 Sales'!H3*'S20-04 Inputs'!$B$6
A4: 45809 | B4: ='S20-04 Sales'!H4*'S20-04 Inputs'!$B$2 | C4: ='S20-04 Inputs'!$B$4 | D4: ='S20-04 Inputs'!$B$3 | E4: ='S20-04 Sales'!H4*'S20-04 Inputs'!B9 | F4: ='S20-04 Sales'!H4*'S20-04 Inputs'!$B$6
A5: 45839 | B5: ='S20-04 Sales'!H5*'S20-04 Inputs'!$B$2 | C5: ='S20-04 Inputs'!$B$4 | D5: ='S20-04 Inputs'!$B$3 | E5: ='S20-04 Sales'!H5*'S20-04 Inputs'!B10 | F5: ='S20-04 Sales'!H5*'S20-04 Inputs'!$B$6
A6: 45870 | B6: ='S20-04 Sales'!H6*'S20-04 Inputs'!$B$2 | C6: ='S20-04 Inputs'!$B$4 | D6: ='S20-04 Inputs'!$B$3 | E6: ='S20-04 Sales'!H6*'S20-04 Inputs'!B11 | F6: ='S20-04 Sales'!H6*'S20-04 Inputs'!$B$6
A7: 45901 | B7: ='S20-04 Sales'!H7*'S20-04 Inputs'!$B$2 | C7: ='S20-04 Inputs'!$B$4 | D7: ='S20-04 Inputs'!$B$3 | E7: ='S20-04 Sales'!H7*'S20-04 Inputs'!B12 | F7: ='S20-04 Sales'!H7*'S20-04 Inputs'!$B$6
A8: 45931 | B8: ='S20-04 Sales'!H8*'S20-04 Inputs'!$B$2 | C8: ='S20-04 Inputs'!$B$4*(1+'S20-04 Inputs'!$B$5) | D8: ='S20-04 Inputs'!$B$3 | E8: ='S20-04 Sales'!H8*'S20-04 Inputs'!B13 | F8: ='S20-04 Sales'!H8*'S20-04 Inputs'!$B$6
A9: 45962 | B9: ='S20-04 Sales'!H9*'S20-04 Inputs'!$B$2 | C9: ='S20-04 Inputs'!$B$4*(1+'S20-04 Inputs'!$B$5) | D9: ='S20-04 Inputs'!$B$3 | E9: ='S20-04 Sales'!H9*'S20-04 Inputs'!B14 | F9: ='S20-04 Sales'!H9*'S20-04 Inputs'!$B$6
A10: 45992 | B10: ='S20-04 Sales'!H10*'S20-04 Inputs'!$B$2 | C10: ='S20-04 Inputs'!$B$4*(1+'S20-04 Inputs'!$B$5) | D10: ='S20-04 Inputs'!$B$3 | E10: ='S20-04 Sales'!H10*'S20-04 Inputs'!B15 | F10: ='S20-04 Sales'!H10*'S20-04 Inputs'!$B$6
A11: 46023 | B11: ='S20-04 Sales'!H11*'S20-04 Inputs'!$B$2 | C11: ='S20-04 Inputs'!$B$4*(1+'S20-04 Inputs'!$B$5) | D11: ='S20-04 Inputs'!$B$3 | E11: ='S20-04 Sales'!H11*'S20-04 Inputs'!B16 | F11: ='S20-04 Sales'!H11*'S20-04 Inputs'!$B$6
A12: 46054 | B12: ='S20-04 Sales'!H12*'S20-04 Inputs'!$B$2 | C12: ='S20-04 Inputs'!$B$4*(1+'S20-04 Inputs'!$B$5) | D12: ='S20-04 Inputs'!$B$3 | E12: ='S20-04 Sales'!H12*'S20-04 Inputs'!B17 | F12: ='S20-04 Sales'!H12*'S20-04 Inputs'!$B$6
A13: 46082 | B13: ='S20-04 Sales'!H13*'S20-04 Inputs'!$B$2 | C13: ='S20-04 Inputs'!$B$4*(1+'S20-04 Inputs'!$B$5) | D13: ='S20-04 Inputs'!$B$3 | E13: ='S20-04 Sales'!H13*'S20-04 Inputs'!B18 | F13: ='S20-04 Sales'!H13*'S20-04 Inputs'!$B$6

Sheet S20-04
A1: Line item | B1: Apr-25 | C1: May-25 | D1: Jun-25 | E1: Jul-25 | F1: Aug-25 | G1: Sep-25 | H1: Oct-25 | I1: Nov-25 | J1: Dec-25 | K1: Jan-26 | L1: Feb-26 | M1: Mar-26 | N1: FY total
A2: Revenue | B2: ='S20-04 Sales'!H2 | C2: ='S20-04 Sales'!H3 | D2: ='S20-04 Sales'!H4 | E2: ='S20-04 Sales'!H5 | F2: ='S20-04 Sales'!H6 | G2: ='S20-04 Sales'!H7 | H2: ='S20-04 Sales'!H8 | I2: ='S20-04 Sales'!H9 | J2: ='S20-04 Sales'!H10 | K2: ='S20-04 Sales'!H11 | L2: ='S20-04 Sales'!H12 | M2: ='S20-04 Sales'!H13 | N2: =SUM(B2:M2)
A3: COGS | B3: ='S20-04 Costs'!B2 | C3: ='S20-04 Costs'!B3 | D3: ='S20-04 Costs'!B4 | E3: ='S20-04 Costs'!B5 | F3: ='S20-04 Costs'!B6 | G3: ='S20-04 Costs'!B7 | H3: ='S20-04 Costs'!B8 | I3: ='S20-04 Costs'!B9 | J3: ='S20-04 Costs'!B10 | K3: ='S20-04 Costs'!B11 | L3: ='S20-04 Costs'!B12 | M3: ='S20-04 Costs'!B13 | N3: =SUM(B3:M3)
A4: Gross profit | B4: =B2-B3 | C4: =C2-C3 | D4: =D2-D3 | E4: =E2-E3 | F4: =F2-F3 | G4: =G2-G3 | H4: =H2-H3 | I4: =I2-I3 | ... M4: =M2-M3 | N4: =SUM(B4:M4)
A5: Gross margin % | B5: =B4/B2 | C5: =C4/C2 | D5: =D4/D2 | E5: =E4/E2 | F5: =F4/F2 | G5: =G4/G2 | H5: =H4/H2 | I5: =I4/I2 | ... N5: =N4/N2
A6: Salaries | B6: ='S20-04 Costs'!C2 | C6: ='S20-04 Costs'!C3 | D6: ='S20-04 Costs'!C4 | E6: ='S20-04 Costs'!C5 | F6: ='S20-04 Costs'!C6 | G6: ='S20-04 Costs'!C7 | H6: ='S20-04 Costs'!C8 | I6: ='S20-04 Costs'!C9 | J6: ='S20-04 Costs'!C10 | K6: ='S20-04 Costs'!C11 | L6: ='S20-04 Costs'!C12 | M6: ='S20-04 Costs'!C13 | N6: =SUM(B6:M6)
A7: Rent | B7: ='S20-04 Costs'!D2 | C7: ='S20-04 Costs'!D3 | D7: ='S20-04 Costs'!D4 | E7: ='S20-04 Costs'!D5 | F7: ='S20-04 Costs'!D6 | G7: ='S20-04 Costs'!D7 | H7: ='S20-04 Costs'!D8 | I7: ='S20-04 Costs'!D9 | J7: ='S20-04 Costs'!D10 | K7: ='S20-04 Costs'!D11 | L7: ='S20-04 Costs'!D12 | M7: ='S20-04 Costs'!D13 | N7: =SUM(B7:M7)
A8: Commission | B8: ='S20-04 Costs'!E2 | C8: ='S20-04 Costs'!E3 | D8: ='S20-04 Costs'!E4 | E8: ='S20-04 Costs'!E5 | F8: ='S20-04 Costs'!E6 | G8: ='S20-04 Costs'!E7 | H8: ='S20-04 Costs'!E8 | I8: ='S20-04 Costs'!E9 | J8: ='S20-04 Costs'!E10 | K8: ='S20-04 Costs'!E11 | L8: ='S20-04 Costs'!E12 | M8: ='S20-04 Costs'!E13 | N8: =SUM(B8:M8)
A9: Other expenses | B9: ='S20-04 Costs'!F2 | C9: ='S20-04 Costs'!F3 | D9: ='S20-04 Costs'!F4 | E9: ='S20-04 Costs'!#REF! | F9: ='S20-04 Costs'!F6 | G9: ='S20-04 Costs'!F7 | H9: ='S20-04 Costs'!F8 | I9: ='S20-04 Costs'!F9 | J9: ='S20-04 Costs'!F10 | K9: ='S20-04 Costs'!F11 | L9: ='S20-04 Costs'!F12 | M9: ='S20-04 Costs'!F13 | N9: =SUM(B9:M9)
A10: Total operating expenses | B10: =SUM(B6:B9) | C10: =SUM(C6:C9) | D10: =SUM(D6:D9) | E10: =SUM(E6:E9) | F10: =SUM(F6:F9) | G10: =SUM(G6:G9) | H10: =SUM(H6:H9) | I10: =SUM(I6:I9) | ... M10: =SUM(M6:M9) | N10: =SUM(B10:M10)
A11: EBITDA | B11: =B4-B10 | C11: =C4-C10 | D11: =D4-D10 | E11: =E4-E10 | F11: =F4-F10 | G11: =G4-G10 | H11: =H4-H10 | I11: =I4-I10 | ... M11: =M4-M10 | N11: =SUM(B11:L11)
A12: EBITDA margin % | B12: =B11/B2 | C12: =C11/C2 | D12: =D11/D2 | E12: =E11/E2 | F12: =F11/F2 | G12: =G11/G2 | H12: =H11/H2 | I12: =I11/I2 | ... N12: =N11/N2
A15: Hand check: FY revenue (sum of Sales H2:H13)

Sheet S20-04 Done
A1: Fix log: four problems found by Claude, each fix approved and checked
A3: # | B3: Cell | C3: Problem | D3: Before | E3: After
A4: 1 | B4: 'S20-04'!E9 | C4: #REF! error in July other expenses | D4: ='S20-04 Costs'!#REF! | E4: ='S20-04 Costs'!F5
A5: 2 | B5: 'S20-04'!N11 | C5: FY EBITDA misses March | D5: =SUM(B11:L11) | E5: =SUM(B11:M11)
A6: 3 | B6: 'S20-04 Sales'!H8 | C6: October revenue typed as a stale number | D6: a typed number | E6: =B8*C8+D8*E8+F8*G8
A7: 4 | B7: 'S20-04 Costs'!E2:E13 | C7: Commission reference drifts to blank cells (no $) | D7: ='S20-04 Sales'!H3*'S20-04 Inputs'!B8 | E7: ='S20-04 Sales'!H3*'S20-04 Inputs'!$B$7
A10: Correct FY revenue | B10: 101606325
A11: Correct FY EBITDA | B11: 10503444
A13: Values above are what 'S20-04'!N2 and N11 show after all four fixes.

Sheet S20-05
A1: Customer name | B1: Phone | C1: City | D1: State | E1: Onboarded on | F1: GSTIN | H1: Hand check
A2: sharma electricals | B2: 98220 45671 | C2: Pune | D2: MH | E2: 03/04/2026 | F2: 27aaqfs1234k1z5 | H2: Rows in original
A3: KAVERI TRADERS | B3: +91-9845012345 | C3: Bengaluru | D3: Karnataka | E3: 2026-04-07 | F3: 29AAFFK7390P1Z8 | H3: Rows in S20-05 Clean
A4: om sai distributors | B4: 09876543210 | C4: Nashik | D4: Maharastra | E4: 12 Apr 2026 | F4: 27ABMPO2245Q1ZK
A5: Ganga Retail Pvt. Ltd. | B5: 9415 123 456 | C5: Lucknow | D5: U.P. | E5: 15.04.2026 | F5: 09AACCG8812L1Z2
A6: lakshmi agencies | B6: 044-2345 6789 | C6: Chennai | D6: Tamilnadu | E6: Apr 18, 2026 | F6: 33AAEFL5521M1Z9
A7: NAVKAR SUPPLIES | B7: +91 99250 11223 | C7: Surat | D7: GJ | E7: 21-04-26 | F7: 24AAJFN3307B1Z4
A8: Royal Book House | B8: 9811198111 | C8: New Delhi | D8: Delhi NCR | E8: 02/05/2026 | F8: 07AAHFR6610C1Z7
A9: mahalaxmi mart | B9: 8888 777 666 | C9: Kolhapur | D9: maharashtra | E9: 2026-05-06 | F9: 27aamfm4410d1z3
A10: Sri Venkateswara Traders | B10: +91-9440098765 | C10: Vijayawada | D10: AP | E10: 9 May 2026 | F10: 37AAKFS9902E1Z6
A11: Bharat Steel Traders | B11: 079 2656 1234 | C11: Ahmedabad | D11: Gujarat | E11: 13.05.2026 | F11: 24AACFB6612R1Z1
A12: KALINGA HARDWARE | B12: 9437012345 | C12: Bhubaneswar | D12: Orissa | E12: May 16, 2026 | F12: 21AAGFK1108F1Z0
A13: gupta electricals | B13: +91 9810 555 444 | C13: Gurgaon | D13: HR | E13: 20-05-26 | F13: 06AFKPG3381L1Z6
A14: Malabar Spices Co | B14: 0484 2401234 | C14: Kochi | D14: KL | E14: 01/06/2026 | F14: 32AAHFM7703G1Z5
A15: PONDY TEXTILES | B15: 9443322110 | C15: Puducherry | D15: Pondicherry | E15: 2026-06-04 | F15: 34AAIFP2290H1Z3
... A23: Himalayan Organics | B23: 0135 2711 222 | C23: Dehradun | D23: UK | E23: 02.07.2026 | F23: 05AAQFH1012R1Z9

Sheet S20-05 Done
A1: Customer name | B1: Phone | C1: City | D1: State | E1: Onboarded on | F1: GSTIN | G1: Changes | I1: Original sheet S20-05 left unchanged; this is the cleaned copy with an audit trail in column G.
A2: Sharma Electricals | B2: 9822045671 | C2: Pune | D2: Maharashtra | E2: 46115 | F2: 27AAQFS1234K1Z5 | G2: name case/spaces; phone to digits; state MH → Maharashtra; date to real date; GSTIN upper case
A3: Kaveri Traders | B3: 9845012345 | C3: Bengaluru | D3: Karnataka | E3: 46119 | F3: 29AAFFK7390P1Z8 | G3: name case/spaces; phone to digits; date to real date
A4: Om Sai Distributors | B4: 9876543210 | C4: Nashik | D4: Maharashtra | E4: 46124 | F4: 27ABMPO2245Q1ZK | G4: name case/spaces; phone to digits; state Maharastra → Maharashtra; date to real date
A5: Ganga Retail Pvt. Ltd. | B5: 9415123456 | C5: Lucknow | D5: Uttar Pradesh | E5: 46127 | F5: 09AACCG8812L1Z2 | G5: phone to digits; state U.P. → Uttar Pradesh; date to real date
A6: Lakshmi Agencies | B6: 04423456789 | C6: Chennai | D6: Tamil Nadu | E6: 46130 | F6: 33AAEFL5521M1Z9 | G6: name case/spaces; phone to digits; state Tamilnadu → Tamil Nadu; date to real date
A7: Navkar Supplies | B7: 9925011223 | C7: Surat | D7: Gujarat | E7: 46133 | F7: 24AAJFN3307B1Z4 | G7: name case/spaces; phone to digits; state GJ → Gujarat; date to real date
A8: Royal Book House | B8: 9811198111 | C8: New Delhi | D8: Delhi | E8: 46144 | F8: 07AAHFR6610C1Z7 | G8: state Delhi NCR → Delhi; date to real date
A9: Mahalaxmi Mart | B9: 8888777666 | C9: Kolhapur | D9: Maharashtra | E9: 46148 | F9: 27AAMFM4410D1Z3 | G9: name case/spaces; phone to digits; state maharashtra → Maharashtra; date to real date; GSTIN upper case
A10: Sri Venkateswara Traders | B10: 9440098765 | C10: Vijayawada | D10: Andhra Pradesh | E10: 46151 | F10: 37AAKFS9902E1Z6 | G10: phone to digits; state AP → Andhra Pradesh; date to real date
A11: Bharat Steel Traders | B11: 07926561234 | C11: Ahmedabad | D11: Gujarat | E11: 46155 | F11: 24AACFB6612R1Z1 | G11: phone to digits; state Gujarat → Gujarat; date to real date
A12: Kalinga Hardware | B12: 9437012345 | C12: Bhubaneswar | D12: Odisha | E12: 46158 | F12: 21AAGFK1108F1Z0 | G12: name case/spaces; state Orissa → Odisha; date to real date
A13: Gupta Electricals | B13: 9810555444 | C13: Gurgaon | D13: Haryana | E13: 46162 | F13: 06AFKPG3381L1Z6 | G13: name case/spaces; phone to digits; state HR → Haryana; date to real date
... A23: Himalayan Organics | B23: 01352711222 | C23: Dehradun | D23: Uttarakhand | E23: 46205 | F23: 05AAQFH1012R1Z9 | G23: phone to digits; state UK → Uttarakhand; date to real date

Sheet S20-06
A1: Brief: FY 2026-27 monthly budget for Tandoor Tales, a cloud kitchen in Pune
A2: Orders per day in April 2026: 180
A3: Orders grow 3% every month after April
A4: Average order value: ₹420
A5: Days per month: 30
A6: Food cost: 32% of revenue
A7: Delivery platform commission: 22% of revenue
A8: Kitchen rent: ₹1,20,000 per month
A9: Staff salaries: ₹3,80,000 per month
A10: Marketing: 5% of revenue
A11: Show monthly EBITDA (revenue minus all costs above) and the FY total
A13: Hand check: April revenue = 180 orders x 30 days x ₹420

Sheet S20-06 Done
A1: Tandoor Tales cloud kitchen, Pune: FY 2026-27 budget (built by Claude from the brief, checked)
A2: Inputs
A3: Orders per day (April) | B3: 180
A4: Monthly growth in orders | B4: 0.03
A5: Average order value | B5: 420
A6: Days per month | B6: 30
A7: Food cost % of revenue | B7: 0.32
A8: Platform commission % of revenue | B8: 0.22
A9: Kitchen rent per month | B9: 120000
A10: Staff salaries per month | B10: 380000
A11: Marketing % of revenue | B11: 0.05
A13: Line item | B13: Apr-26 | C13: May-26 | D13: Jun-26 | E13: Jul-26 | F13: Aug-26 | G13: Sep-26 | H13: Oct-26 | I13: Nov-26 | J13: Dec-26 | K13: Jan-27 | L13: Feb-27 | M13: Mar-27 | N13: FY total
A14: Orders per day | B14: =$B$3 | C14: =B14*(1+$B$4) | D14: =C14*(1+$B$4) | E14: =D14*(1+$B$4) | F14: =E14*(1+$B$4) | G14: =F14*(1+$B$4) | H14: =G14*(1+$B$4) | I14: =H14*(1+$B$4) | J14: =I14*(1+$B$4) | ... M14: =L14*(1+$B$4) | N14: =AVERAGE(B14:M14)
A15: Orders in month | B15: =B14*$B$6 | C15: =C14*$B$6 | D15: =D14*$B$6 | E15: =E14*$B$6 | F15: =F14*$B$6 | G15: =G14*$B$6 | H15: =H14*$B$6 | I15: =I14*$B$6 | ... M15: =M14*$B$6 | N15: =SUM(B15:M15)
A16: Revenue | B16: =B15*$B$5 | C16: =C15*$B$5 | D16: =D15*$B$5 | E16: =E15*$B$5 | F16: =F15*$B$5 | G16: =G15*$B$5 | H16: =H15*$B$5 | I16: =I15*$B$5 | ... M16: =M15*$B$5 | N16: =SUM(B16:M16)
A17: Food cost | B17: =B16*$B$7 | C17: =C16*$B$7 | D17: =D16*$B$7 | E17: =E16*$B$7 | F17: =F16*$B$7 | G17: =G16*$B$7 | H17: =H16*$B$7 | I17: =I16*$B$7 | ... M17: =M16*$B$7 | N17: =SUM(B17:M17)
A18: Platform commission | B18: =B16*$B$8 | C18: =C16*$B$8 | D18: =D16*$B$8 | E18: =E16*$B$8 | F18: =F16*$B$8 | G18: =G16*$B$8 | H18: =H16*$B$8 | I18: =I16*$B$8 | ... M18: =M16*$B$8 | N18: =SUM(B18:M18)
A19: Contribution | B19: =B16-B17-B18 | C19: =C16-C17-C18 | D19: =D16-D17-D18 | E19: =E16-E17-E18 | F19: =F16-F17-F18 | G19: =G16-G17-G18 | H19: =H16-H17-H18 | I19: =I16-I17-I18 | ... M19: =M16-M17-M18 | N19: =SUM(B19:M19)
A20: Kitchen rent | B20: =$B$9 | C20: =$B$9 | D20: =$B$9 | E20: =$B$9 | F20: =$B$9 | G20: =$B$9 | H20: =$B$9 | I20: =$B$9 | ... M20: =$B$9 | N20: =SUM(B20:M20)
A21: Staff salaries | B21: =$B$10 | C21: =$B$10 | D21: =$B$10 | E21: =$B$10 | F21: =$B$10 | G21: =$B$10 | H21: =$B$10 | I21: =$B$10 | ... M21: =$B$10 | N21: =SUM(B21:M21)
A22: Marketing | B22: =B16*$B$11 | C22: =C16*$B$11 | D22: =D16*$B$11 | E22: =E16*$B$11 | F22: =F16*$B$11 | G22: =G16*$B$11 | H22: =H16*$B$11 | I22: =I16*$B$11 | ... M22: =M16*$B$11 | N22: =SUM(B22:M22)
A23: EBITDA | B23: =B19-B20-B21-B22 | C23: =C19-C20-C21-C22 | D23: =D19-D20-D21-D22 | E23: =E19-E20-E21-E22 | F23: =F19-F20-F21-F22 | G23: =G19-G20-G21-G22 | H23: =H19-H20-H21-H22 | I23: =I19-I20-I21-I22 | ... M23: =M19-M20-M21-M22 | N23: =SUM(B23:M23)
A24: EBITDA margin % | B24: =B23/B16 | C24: =C23/C16 | D24: =D23/D16 | E24: =E23/E16 | F24: =F23/F16 | G24: =G23/G16 | H24: =H23/H16 | I24: =I23/I16 | ... N24: =N23/N16

Sheet S20-07
A1: Tandoor Tales cloud kitchen, Pune: FY 2026-27 budget
A2: Inputs
A3: Orders per day (April) | B3: 180
A4: Monthly growth in orders | B4: 0.03
A5: Average order value | B5: 420
A6: Days per month | B6: 30
A7: Food cost % of revenue | B7: 0.32
A8: Platform commission % of revenue | B8: 0.22
A9: Kitchen rent per month | B9: 120000
A10: Staff salaries per month | B10: 380000
A11: Marketing % of revenue | B11: 0.05
A13: Line item | B13: Apr-26 | C13: May-26 | D13: Jun-26 | E13: Jul-26 | F13: Aug-26 | G13: Sep-26 | H13: Oct-26 | I13: Nov-26 | J13: Dec-26 | K13: Jan-27 | L13: Feb-27 | M13: Mar-27 | N13: FY total
A14: Orders per day | B14: =$B$3 | C14: =B14*(1+$B$4) | D14: =C14*(1+$B$4) | E14: =D14*(1+$B$4) | F14: =E14*(1+$B$4) | G14: =F14*(1+$B$4) | H14: =G14*(1+$B$4) | I14: =H14*(1+$B$4) | J14: =I14*(1+$B$4) | ... M14: =L14*(1+$B$4) | N14: =AVERAGE(B14:M14)
A15: Orders in month | B15: =B14*$B$6 | C15: =C14*$B$6 | D15: =D14*$B$6 | E15: =E14*$B$6 | F15: =F14*$B$6 | G15: =G14*$B$6 | H15: =H14*$B$6 | I15: =I14*$B$6 | ... M15: =M14*$B$6 | N15: =SUM(B15:M15)
A16: Revenue | B16: =B15*$B$5 | C16: =C15*$B$5 | D16: =D15*$B$5 | E16: =E15*$B$5 | F16: =F15*$B$5 | G16: =G15*$B$5 | H16: =H15*$B$5 | I16: =I15*$B$5 | ... M16: =M15*$B$5 | N16: =SUM(B16:M16)
A17: Food cost | B17: =B16*$B$7 | C17: =C16*$B$7 | D17: =D16*$B$7 | E17: =E16*$B$7 | F17: =F16*$B$7 | G17: =G16*$B$7 | H17: =H16*$B$7 | I17: =I16*$B$7 | ... M17: =M16*$B$7 | N17: =SUM(B17:M17)
A18: Platform commission | B18: =B16*$B$8 | C18: =C16*$B$8 | D18: =D16*$B$8 | E18: =E16*$B$8 | F18: =F16*$B$8 | G18: =G16*$B$8 | H18: =H16*$B$8 | I18: =I16*$B$8 | ... M18: =M16*$B$8 | N18: =SUM(B18:M18)
A19: Contribution | B19: =B16-B17-B18 | C19: =C16-C17-C18 | D19: =D16-D17-D18 | E19: =E16-E17-E18 | F19: =F16-F17-F18 | G19: =G16-G17-G18 | H19: =H16-H17-H18 | I19: =I16-I17-I18 | ... M19: =M16-M17-M18 | N19: =SUM(B19:M19)
A20: Kitchen rent | B20: =$B$9 | C20: =$B$9 | D20: =$B$9 | E20: =$B$9 | F20: =$B$9 | G20: =$B$9 | H20: =$B$9 | I20: =$B$9 | ... M20: =$B$9 | N20: =SUM(B20:M20)
A21: Staff salaries | B21: =$B$10 | C21: =$B$10 | D21: =$B$10 | E21: =$B$10 | F21: =$B$10 | G21: =$B$10 | H21: =$B$10 | I21: =$B$10 | ... M21: =$B$10 | N21: =SUM(B21:M21)
A22: Marketing | B22: =B16*$B$11 | C22: =C16*$B$11 | D22: =D16*$B$11 | E22: =E16*$B$11 | F22: =F16*$B$11 | G22: =G16*$B$11 | H22: =H16*$B$11 | I22: =I16*$B$11 | ... M22: =M16*$B$11 | N22: =SUM(B22:M22)
A23: EBITDA | B23: =B19-B20-B21-B22 | C23: =C19-C20-C21-C22 | D23: =D19-D20-D21-D22 | E23: =E19-E20-E21-E22 | F23: =F19-F20-F21-F22 | G23: =G19-G20-G21-G22 | H23: =H19-H20-H21-H22 | I23: =I19-I20-I21-I22 | ... M23: =M19-M20-M21-M22 | N23: =SUM(B23:M23)
A24: EBITDA margin % | B24: =B23/B16 | C24: =C23/C16 | D24: =D23/D16 | E24: =E23/E16 | F24: =F23/F16 | G24: =G23/G16 | H24: =H23/H16 | I24: =I23/I16 | ... N24: =N23/N16

Sheet S20-07 Done
A1: Tandoor Tales: budget with Base / Best / Worst scenarios
A2: Inputs | P2: Scenario (1 Base, 2 Best, 3 Worst) | Q2: 1
A3: Orders per day (April) | B3: =CHOOSE($Q$2,Q5,R5,S5)
A4: Monthly growth in orders | B4: =CHOOSE($Q$2,Q6,R6,S6) | P4: Input | Q4: Base | R4: Best | S4: Worst
A5: Average order value | B5: =CHOOSE($Q$2,Q7,R7,S7) | P5: Orders per day (April) | Q5: 180 | R5: 210 | S5: 150
A6: Days per month | B6: 30 | P6: Monthly growth in orders | Q6: 0.03 | R6: 0.04 | S6: 0.015
A7: Food cost % of revenue | B7: =CHOOSE($Q$2,Q8,R8,S8) | P7: Average order value | Q7: 420 | R7: 450 | S7: 390
A8: Platform commission % of revenue | B8: 0.22 | P8: Food cost % of revenue | Q8: 0.32 | R8: 0.3 | S8: 0.35
A9: Kitchen rent per month | B9: 120000
A10: Staff salaries per month | B10: 380000 | P10: B3, B4, B5 and B7 now pick their value from the chosen scenario.
A11: Marketing % of revenue | B11: 0.05
A13: Line item | B13: Apr-26 | C13: May-26 | D13: Jun-26 | E13: Jul-26 | F13: Aug-26 | G13: Sep-26 | H13: Oct-26 | I13: Nov-26 | J13: Dec-26 | K13: Jan-27 | L13: Feb-27 | M13: Mar-27 | N13: FY total
A14: Orders per day | B14: =$B$3 | C14: =B14*(1+$B$4) | D14: =C14*(1+$B$4) | E14: =D14*(1+$B$4) | F14: =E14*(1+$B$4) | G14: =F14*(1+$B$4) | H14: =G14*(1+$B$4) | I14: =H14*(1+$B$4) | J14: =I14*(1+$B$4) | ... M14: =L14*(1+$B$4) | N14: =AVERAGE(B14:M14)
A15: Orders in month | B15: =B14*$B$6 | C15: =C14*$B$6 | D15: =D14*$B$6 | E15: =E14*$B$6 | F15: =F14*$B$6 | G15: =G14*$B$6 | H15: =H14*$B$6 | I15: =I14*$B$6 | ... M15: =M14*$B$6 | N15: =SUM(B15:M15)
A16: Revenue | B16: =B15*$B$5 | C16: =C15*$B$5 | D16: =D15*$B$5 | E16: =E15*$B$5 | F16: =F15*$B$5 | G16: =G15*$B$5 | H16: =H15*$B$5 | I16: =I15*$B$5 | ... M16: =M15*$B$5 | N16: =SUM(B16:M16)
A17: Food cost | B17: =B16*$B$7 | C17: =C16*$B$7 | D17: =D16*$B$7 | E17: =E16*$B$7 | F17: =F16*$B$7 | G17: =G16*$B$7 | H17: =H16*$B$7 | I17: =I16*$B$7 | ... M17: =M16*$B$7 | N17: =SUM(B17:M17)
A18: Platform commission | B18: =B16*$B$8 | C18: =C16*$B$8 | D18: =D16*$B$8 | E18: =E16*$B$8 | F18: =F16*$B$8 | G18: =G16*$B$8 | H18: =H16*$B$8 | I18: =I16*$B$8 | ... M18: =M16*$B$8 | N18: =SUM(B18:M18)
A19: Contribution | B19: =B16-B17-B18 | C19: =C16-C17-C18 | D19: =D16-D17-D18 | E19: =E16-E17-E18 | F19: =F16-F17-F18 | G19: =G16-G17-G18 | H19: =H16-H17-H18 | I19: =I16-I17-I18 | ... M19: =M16-M17-M18 | N19: =SUM(B19:M19)
A20: Kitchen rent | B20: =$B$9 | C20: =$B$9 | D20: =$B$9 | E20: =$B$9 | F20: =$B$9 | G20: =$B$9 | H20: =$B$9 | I20: =$B$9 | ... M20: =$B$9 | N20: =SUM(B20:M20)
A21: Staff salaries | B21: =$B$10 | C21: =$B$10 | D21: =$B$10 | E21: =$B$10 | F21: =$B$10 | G21: =$B$10 | H21: =$B$10 | I21: =$B$10 | ... M21: =$B$10 | N21: =SUM(B21:M21)
A22: Marketing | B22: =B16*$B$11 | C22: =C16*$B$11 | D22: =D16*$B$11 | E22: =E16*$B$11 | F22: =F16*$B$11 | G22: =G16*$B$11 | H22: =H16*$B$11 | I22: =I16*$B$11 | ... M22: =M16*$B$11 | N22: =SUM(B22:M22)
A23: EBITDA | B23: =B19-B20-B21-B22 | C23: =C19-C20-C21-C22 | D23: =D19-D20-D21-D22 | E23: =E19-E20-E21-E22 | F23: =F19-F20-F21-F22 | G23: =G19-G20-G21-G22 | H23: =H19-H20-H21-H22 | I23: =I19-I20-I21-I22 | ... M23: =M19-M20-M21-M22 | N23: =SUM(B23:M23)
A24: EBITDA margin % | B24: =B23/B16 | C24: =C23/C16 | D24: =D23/D16 | E24: =E23/E16 | F24: =F23/F16 | G24: =G23/G16 | H24: =H23/H16 | I24: =I23/I16 | ... N24: =N23/N16

Sheet S20-08
A1: Check | B1: Per PDF | C1: From extracted sheet | D1: Difference
A2: Total withdrawals (Dr) | B2: 105338.15 | D2: =IF(C2="","",ROUND(C2-B2,2))
A3: Total deposits (Cr) | B3: 132161 | D3: =IF(C3="","",ROUND(C3-B3,2))
A4: Closing balance | B4: 91141.1 | D4: =IF(C4="","",ROUND(C4-B4,2))
A5: Number of transactions | B5: 22 | D5: =IF(C5="","",ROUND(C5-B5,2))
A7: Opening balance (PDF) | B7: 64318.25
A9: Source: data/Sahyadri_Bank_Statement_Sep2026.pdf (sample statement, fictional bank)

Sheet S20-08 Done
A1: Date | B1: Description | C1: Reference | D1: Debit | E1: Credit | F1: Balance | G1: Category | I1: Check | J1: Per PDF | K1: From sheet | L1: Difference
A2: 46266 | B2: NEFT CR-ACME ANALYTICS PVT LTD-SALARY SEP | C2: 258441420184 | E2: 112450 | F2: 176768.25 | G2: Salary | I2: Total withdrawals (Dr) | J2: 105338.15 | K2: =SUM(D2:D23) | L2: =K2-J2
A3: 46267 | B3: IMPS-RENT SEP-SURESH KULKARNI | C3: 221912388757 | D3: 28000 | F3: 148768.25 | G3: Rent | I3: Total deposits (Cr) | J3: 132161 | K3: =SUM(E2:E23) | L3: =K3-J3
A4: 46268 | B4: ACH DR-HOME LOAN EMI-LAN 88213409 | C4: 937735831395 | D4: 21850 | F4: 126918.25 | G4: EMI | I4: Closing balance | J4: 91141.1 | K4: =L7-K2+K3 | L4: =K4-J4
A5: 46270 | B5: UPI-SWIGGY-swiggy@axisbank | C5: 537006185622 | D5: 486 | F5: 126432.25 | G5: Food | I5: Number of transactions | J5: 22 | K5: =COUNTA(A2:A23) | L5: =K5-J5
A6: 46270 | B6: BILLDESK-MSEDCL ELECTRICITY-CONS 170012345 | C6: 505383506882 | D6: 2340 | F6: 124092.25 | G6: Utilities
A7: 46272 | B7: ACH DR-MF SIP-FOLIO 10293847 | C7: 962911185245 | D7: 10000 | F7: 114092.25 | G7: Investments | I7: Opening balance (PDF) | L7: 64318.25
A8: 46273 | B8: UPI-BIGBASKET-bigbasket@hdfc | C8: 266640869443 | D8: 3215.5 | F8: 110876.75 | G8: Groceries
A9: 46275 | B9: ATM WDL-KOTHRUD PUNE | C9: 464976438616 | D9: 5000 | F9: 105876.75 | G9: Cash | I9: Category | J9: Spent
A10: 46277 | B10: UPI-AMAZON PAY-amazonpay@apl | C10: 937088697460 | D10: 2799 | F10: 103077.75 | G10: Shopping | I10: Cash | J10: =SUMIFS($D$2:$D$23,$G$2:$G$23,I10)
A11: 46278 | B11: UPI-ZOMATO-zomato@kotak | C11: 355363350439 | D11: 612 | F11: 102465.75 | G11: Food | I11: EMI | J11: =SUMIFS($D$2:$D$23,$G$2:$G$23,I11)
A12: 46280 | B12: NEFT CR-R SHAH-FREELANCE DESIGN FEE | C12: 874047150988 | E12: 18000 | F12: 120465.75 | G12: Other income | I12: Food | J12: =SUMIFS($D$2:$D$23,$G$2:$G$23,I12)
A13: 46281 | B13: UPI-JIO PREPAID RECHARGE | C13: 493170303837 | D13: 349 | F13: 120116.75 | G13: Utilities | I13: Groceries | J13: =SUMIFS($D$2:$D$23,$G$2:$G$23,I13)
A14: 46283 | B14: UPI-IRCTC-irctc@sbi | C14: 703721974468 | D14: 1845.6 | F14: 118271.15 | G14: Travel | I14: Health | J14: =SUMIFS($D$2:$D$23,$G$2:$G$23,I14)
A15: 46284 | B15: POS-DMART KOTHRUD | C15: 288049801566 | D15: 4128.75 | F15: 114142.4 | G15: Groceries | I15: Insurance | J15: =SUMIFS($D$2:$D$23,$G$2:$G$23,I15)
A16: 46286 | B16: UPI-SWIGGY INSTAMART | C16: 264383082192 | D16: 734 | F16: 113408.4 | G16: Groceries | I16: Investments | J16: =SUMIFS($D$2:$D$23,$G$2:$G$23,I16)
A17: 46287 | B17: IMPS-TO SELF-SAVINGS A/C XX7710 | C17: 273624786166 | D17: 15000 | F17: 98408.4 | G17: Transfer | I17: Rent | J17: =SUMIFS($D$2:$D$23,$G$2:$G$23,I17)
A18: 46289 | B18: UPI-APOLLO PHARMACY | C18: 965722744299 | D18: 1256 | F18: 97152.4 | G18: Health | I18: Shopping | J18: =SUMIFS($D$2:$D$23,$G$2:$G$23,I18)
A19: 46290 | B19: BILLDESK-MAHANAGAR GAS-BP 4401928 | C19: 871171718969 | D19: 890 | F19: 96262.4 | G19: Utilities | I19: Transfer | J19: =SUMIFS($D$2:$D$23,$G$2:$G$23,I19)
A20: 46291 | B20: UPI-UBER INDIA-uber@icici | C20: 785549067929 | D20: 412.3 | F20: 95850.1 | G20: Travel | I20: Travel | J20: =SUMIFS($D$2:$D$23,$G$2:$G$23,I20)
A21: 46292 | B21: NEFT CR-AMAZON REFUND-ORDER 402-7781 | C21: 699669494556 | E21: 1299 | F21: 97149.1 | G21: Refund | I21: Utilities | J21: =SUMIFS($D$2:$D$23,$G$2:$G$23,I21)
A22: 46293 | B22: ACH DR-LIC PREMIUM-POLICY 9123456 | C22: 976921063796 | D22: 6420 | F22: 90729.1 | G22: Insurance
A23: 46295 | B23: INT CR-SAVINGS INTEREST JUL-SEP | C23: 549439579805 | E23: 412 | F23: 91141.1 | G23: Interest

Sheet S20-10
A1: Date | B1: Vendor | C1: Description | D1: Amount | E1: Category | J1: Hand check
A2: 03/07/2026 | B2: SWIGGY LTD | C2: Team lunch, sales review | D2: 2840 | E2: Meals | J2: Total Amount (must not change)
A3: 2026-07-04 | B3: Uber India | C3: Cab to client office, Andheri | D3: 486 | E3: Travel | J3: Sum of the AI's category totals
A4: 5 Jul 2026 | B4: swiggy | C4: Working dinner, month-end close | D4: 1620
A5: 07.07.2026 | B5: OLA CABS | C5: Airport drop, Mumbai | D5: 1245
A6: Jul 9, 2026 | B6: Indigo | C6: Flight Mumbai to Bengaluru | D6: 6850 | E6: Travel
A7: 11-07-26 | B7: AMAZON.IN | C7: Printer toner cartridge | D7: 3299 | E7: Office supplies
A8: 13/07/2026 | B8: uber | C8: Cab, Bengaluru client visit | D8: 612
A9: 2026-07-15 | B9: Taj Hotels | C9: Hotel, 2 nights Bengaluru | D9: 14200 | E9: Hotel
A10: 18 Jul 2026 | B10: Zomato Ltd. | C10: Client lunch | D10: 3150
A11: 20.07.2026 | B11: Amazon | C11: Laptop stand | D11: 1899
A12: Jul 22, 2026 | B12: Ola | C12: Cab to station | D12: 340 | E12: Travel
A13: 24-07-26 | B13: INDIGO AIRLINES | C13: Flight Bengaluru to Mumbai | D13: 5975
A14: 26/07/2026 | B14: Swiggy Instamart | C14: Snacks for office meeting | D14: 910 | E14: Meals
A15: 2026-07-28 | B15: Airtel | C15: Mobile bill July | D15: 799 | E15: Phone and internet
A16: 29 Jul 2026 | B16: JIO FIBER | C16: Home internet, WFH | D16: 1178
A17: 30.07.2026 | B17: Staples India | C17: Notebooks and pens | D17: 640
A18: Jul 31, 2026 | B18: Zomato | C18: Team dinner, quarter close | D18: 4380 | E18: Meals
A19: 31-07-26 | B19: uber india systems | C19: Late night cab home | D19: 528

Sheet S20-10 Claude
A1: Date | B1: Vendor | C1: Description | D1: Amount | E1: Category | J1: Hand check
A2: 03/07/2026 | B2: SWIGGY LTD | C2: Team lunch, sales review | D2: 2840 | E2: Meals | J2: Total Amount (must not change)
A3: 2026-07-04 | B3: Uber India | C3: Cab to client office, Andheri | D3: 486 | E3: Travel | J3: Sum of the AI's category totals
A4: 5 Jul 2026 | B4: swiggy | C4: Working dinner, month-end close | D4: 1620
A5: 07.07.2026 | B5: OLA CABS | C5: Airport drop, Mumbai | D5: 1245
A6: Jul 9, 2026 | B6: Indigo | C6: Flight Mumbai to Bengaluru | D6: 6850 | E6: Travel
A7: 11-07-26 | B7: AMAZON.IN | C7: Printer toner cartridge | D7: 3299 | E7: Office supplies
A8: 13/07/2026 | B8: uber | C8: Cab, Bengaluru client visit | D8: 612
A9: 2026-07-15 | B9: Taj Hotels | C9: Hotel, 2 nights Bengaluru | D9: 14200 | E9: Hotel
A10: 18 Jul 2026 | B10: Zomato Ltd. | C10: Client lunch | D10: 3150
A11: 20.07.2026 | B11: Amazon | C11: Laptop stand | D11: 1899
A12: Jul 22, 2026 | B12: Ola | C12: Cab to station | D12: 340 | E12: Travel
A13: 24-07-26 | B13: INDIGO AIRLINES | C13: Flight Bengaluru to Mumbai | D13: 5975
A14: 26/07/2026 | B14: Swiggy Instamart | C14: Snacks for office meeting | D14: 910 | E14: Meals
A15: 2026-07-28 | B15: Airtel | C15: Mobile bill July | D15: 799 | E15: Phone and internet
A16: 29 Jul 2026 | B16: JIO FIBER | C16: Home internet, WFH | D16: 1178
A17: 30.07.2026 | B17: Staples India | C17: Notebooks and pens | D17: 640
A18: Jul 31, 2026 | B18: Zomato | C18: Team dinner, quarter close | D18: 4380 | E18: Meals
A19: 31-07-26 | B19: uber india systems | C19: Late night cab home | D19: 528

Sheet S20-10 Done
A1: Date | B1: Vendor | C1: Description | D1: Amount | E1: Category | G1: Category | H1: Total
A2: 46206 | B2: Swiggy | C2: Team lunch, sales review | D2: 2840 | E2: Meals | G2: Meals | H2: =SUMIFS($D$2:$D$19,$E$2:$E$19,G2)
A3: 46207 | B3: Uber | C3: Cab to client office, Andheri | D3: 486 | E3: Travel | G3: Travel | H3: =SUMIFS($D$2:$D$19,$E$2:$E$19,G3)
A4: 46208 | B4: Swiggy | C4: Working dinner, month-end close | D4: 1620 | E4: Meals | G4: Hotel | H4: =SUMIFS($D$2:$D$19,$E$2:$E$19,G4)
A5: 46210 | B5: Ola | C5: Airport drop, Mumbai | D5: 1245 | E5: Travel | G5: Office supplies | H5: =SUMIFS($D$2:$D$19,$E$2:$E$19,G5)
A6: 46212 | B6: IndiGo | C6: Flight Mumbai to Bengaluru | D6: 6850 | E6: Travel | G6: Phone and internet | H6: =SUMIFS($D$2:$D$19,$E$2:$E$19,G6)
A7: 46214 | B7: Amazon | C7: Printer toner cartridge | D7: 3299 | E7: Office supplies | G7: Total | H7: =SUM(H2:H6)
A8: 46216 | B8: Uber | C8: Cab, Bengaluru client visit | D8: 612 | E8: Travel
A9: 46218 | B9: Taj Hotels | C9: Hotel, 2 nights Bengaluru | D9: 14200 | E9: Hotel
A10: 46221 | B10: Zomato | C10: Client lunch | D10: 3150 | E10: Meals | G10: What we compared | H10: Copilot (Edit mode) | I10: Claude in Excel
A11: 46223 | B11: Amazon | C11: Laptop stand | D11: 1899 | E11: Office supplies | G11: Asked before editing? | H11: Plan mode only | I11: Yes, for larger edits
A12: 46225 | B12: Ola | C12: Cab to station | D12: 340 | E12: Travel | G12: Formulas or typed values? | H12: Check each run | I12: Check each run
A13: 46227 | B13: IndiGo | C13: Flight Bengaluru to Mumbai | D13: 5975 | E13: Travel | G13: Explained what changed? | H13: Short summary | I13: Cell-by-cell, with citations
A14: 46229 | B14: Swiggy | C14: Snacks for office meeting | D14: 910 | E14: Meals | G14: Your checking effort | H14: Same: totals + spot checks | I14: Same: totals + spot checks
A15: 46231 | B15: Airtel | C15: Mobile bill July | D15: 799 | E15: Phone and internet
A16: 46232 | B16: Jio | C16: Home internet, WFH | D16: 1178 | E16: Phone and internet
A17: 46233 | B17: Staples | C17: Notebooks and pens | D17: 640 | E17: Office supplies
A18: 46234 | B18: Zomato | C18: Team dinner, quarter close | D18: 4380 | E18: Meals
A19: 46234 | B19: Uber | C19: Late night cab home | D19: 528 | E19: Travel
